Workbook

Sheet Sheet1
A1: Invoice | B1: StockCode | C1: Description | D1: Quantity | E1: InvoiceDate | F1: Price | G1: Customer ID | H1: Country
A2: 503181 | B2: 84792 | C2: ENCHANTED BIRD COATHANGER 5 HOOK | D2: 4 | E2: 40267.599 | F2: 4.65 | H2: United Kingdom
A3: 528386 | B3: 22318 | C3: FIVE HEART HANGING DECORATION | D3: 6 | E3: 40472.772 | F3: 2.95 | G3: 14911 | H3: EIRE
A4: 498594 | B4: 21173 | C4: LOO ROLL METAL SIGN | D4: 1 | E4: 40230.658 | F4: 1.65 | G4: 16797 | H4: United Kingdom
A5: 503245 | B5: 21777 | C5: RECIPE BOX WITH METAL HEART | D5: 2 | E5: 40268.411 | F5: 7.95 | G5: 15216 | H5: United Kingdom
A6: 505756 | B6: 84836 | C6: ZINC METAL HEART DECORATION | D6: 12 | E6: 40294.408 | F6: 1.25 | G6: 14677 | H6: United Kingdom
A7: 496975 | B7: 21559 | C7: STRAWBERRY LUNCHBOX WITH CUTLERY | D7: 6 | E7: 40214.385 | F7: 2.55 | G7: 12712 | H7: Germany
A8: 491584 | B8: 85107 | C8: CUT GLASS T-LIGHT HOLDER OCTAGON | D8: 12 | E8: 40158.538 | F8: 2.55 | G8: 12854 | H8: United Kingdom
A9: 516478 | B9: 22575 | C9: METAL MERRY CHRISTMAS WREATH | D9: 1 | E9: 40379.722 | F9: 1.95 | G9: 17576 | H9: United Kingdom
A10: 502588 | B10: 22083 | C10: PAPER CHAIN KIT RETRO SPOT | D10: 2 | E10: 40262.53 | F10: 2.95 | G10: 16550 | H10: United Kingdom
A11: 515335 | B11: 85014B | C11: RED/WHITE DOTS RUFFLED UMBRELLA | D11: 1 | E11: 40370.597 | F11: 5.95 | G11: 14606 | H11: United Kingdom
A12: 525065 | B12: 21156 | C12: RETROSPOT CHILDRENS APRON | D12: 1 | E12: 40454.603 | F12: 1.95 | G12: 16799 | H12: United Kingdom
A13: 535349 | B13: 84946 | C13: ANTIQUE SILVER TEA GLASS ETCHED | D13: 24 | E13: 40507.703 | F13: 1.25 | G13: 18245 | H13: United Kingdom
A14: 521949 | B14: 82484 | C14: WOOD BLACK BOARD ANT WHITE FINISH | D14: 3 | E14: 40430.719 | F14: 6.45 | G14: 15150 | H14: United Kingdom
A15: 514876 | B15: 22519 | C15: CHILDS GARDEN BRUSH PINK | D15: 36 | E15: 40366.44 | F15: 1.85 | G15: 17511 | H15: United Kingdom
A16: 521162 | B16: 22561 | C16: WOODEN SCHOOL COLOURING SET | D16: 12 | E16: 40423.599 | F16: 1.65 | G16: 12598 | H16: France
A17: 506572 | B17: 20798 | C17: CLEAR MILKSHAKE GLASS | D17: 4 | E17: 40298.549 | F17: 2.1 | G17: 16374 | H17: United Kingdom
A18: 505974 | B18: 48188 | C18: DOOR MAT WELCOME PUPPIES | D18: 1 | E18: 40294.754 | F18: 7.49 | G18: 17449 | H18: United Kingdom
A19: 491622 | B19: 10125 | C19: MINI FUNKY DESIGN TAPES | D19: 1 | E19: 40158.597 | F19: 0.85 | G19: 13415 | H19: U.K.
A20: 509982 | B20: 21696 | C20: SMALL SILVER TRELLIS CANDLEPOT | D20: 6 | E20: 40324.603 | F20: 2.95 | G20: 12924 | H20: United Kingdom
A21: 524611 | B21: 85114B | C21: IVORY ENCHANTED FOREST PLACEMAT | D21: 6 | E21: 40451.401 | F21: 1.65 | G21: 13078 | H21: United Kingdom
A22: 501906 | B22: 22413 | C22: METAL SIGN TAKE IT OR LEAVE IT | D22: 12 | E22: 40258.668 | F22: 2.95 | G22: 17340 | H22: United Kingdom
A23: 505708 | B23: 20979 | C23: 36 PENCILS TUBE RED SPOTTY | D23: 1 | E23: 40293.51 | F23: 1.25 | G23: 13782 | H23: United Kingdom
A24: 497935 | B24: 79323W | C24: WHITE CHERRY LIGHTS | D24: 24 | E24: 40224.449 | F24: 5.45 | G24: 13408 | H24: United Kingdom
A25: 502792 | B25: 15044C | C25: PURPLE PAPER PARASOL | D25: 6 | E25: 40263.631 | F25: 2.95 | G25: 14253 | H25: United Kingdom
A26: 521403 | B26: 21179 | D26: 12 | E26: 40427.43 | F26: 1.25 | G26: 12744 | H26: Singapore
A27: 522904 | B27: 72529W | C27: WHITE ADVENT CANDLE | D27: 1 | E27: 40438.531 | F27: 2.12 | G27: 17765 | H27: United Kingdom
A28: 537810 | B28: 22415 | C28: WHITE TISSUE REAM | D28: 3 | E28: 08-12-2010 13:30 | F28: 7.95 | G28: 15032 | H28: United Kingdom
A29: 520505 | B29: 21258 | C29: VICTORIAN SEWING BOX LARGE | D29: 1 | E29: 40416.535 | F29: 12.75 | G29: 17663 | H29: United Kingdom
A30: 533067 | B30: 21122 | C30: SET/10 PINK POLKADOT PARTY CANDLES | D30: 24 | E30: 40497.718 | F30: 1.25 | G30: 17284 | H30: United Kingdom
A31: 523971 | B31: 21009 | C31: ETCHED GLASS STAR TREE DECORATION | D31: 6 | E31: 40447.578 | F31: 1.25 | G31: 15967 | H31: United Kingdom
A32: 499625 | B32: 15056BL | C32: EDWARDIAN PARASOL BLACK | D32: 2 | E32: 40238.551 | F32: 5.95 | G32: 17965 | H32: United Kingdom
A33: 500147 | B33: 47566 | C33: PARTY BUNTING | D33: 8 | E33: 40241.724 | F33: 4.65 | G33: 15812 | H33: United Kingdom
A34: 537421 | B34: 22569 | C34: FELTCRAFT CUSHION BUTTERFLY | D34: 2 | E34: 40518.642 | F34: 3.75 | G34: 17218 | H34: UNITED KINGDOM
A35: 534526 | B35: 21930 | C35: JUMBO STORAGE BAG SKULLS | D35: 10 | E35: 40505.503 | F35: 1.95 | G35: 15384 | H35: United Kingdom
A36: 503164 | B36: 22556 | C36: PLASTERS IN TIN CIRCUS PARADE | D36: 1 | E36: 40267.552 | F36: 1.65 | G36: 17464 | H36: United Kingdom
A37: 528618 | B37: 21499 | C37: BLUE POLKADOT WRAP | D37: 25 | E37: 40473.713 | F37: 0.42 | G37: 13263 | H37: United Kingdom
A38: 505015 | B38: 22196 | C38: SMALL HEART MEASURING SPOONS | D38: 12 | E38: 40287.562 | F38: 0.85 | G38: 14156 | H38: EIRE
A39: 497272 | B39: 84510B | C39: SET OF 4 FAIRY CAKES COASTERS | D39: 10 | E39: 40217.576 | F39: 1.25 | G39: 17160 | H39: United Kingdom
A40: 518480 | B40: 21890 | C40: S/6 WOODEN SKITTLES IN COTTON BAG | D40: 2 | E40: 40399.515 | F40: 2.95 | G40: 16470 | H40: United Kingdom
A41: 508593 | B41: 21900 | C41: KEY FOB , SHED | D41: 24 | E41: 40315.504 | F41: 0.65 | G41: 13488 | H41: United Kingdom
A42: 505615 | B42: 20712 | C42: JUMBO BAG WOODLAND ANIMALS | D42: 10 | E42: 40291.534 | F42: 1.95 | G42: 15288 | H42: United Kingdom
A43: 523314 | B43: 22551 | C43: PLASTERS IN TIN SPACEBOY | D43: 1 | E43: 40442.558 | F43: 1.65 | H43: United Kingdom
A44: 530538 | B44: 21563 | C44: RED HEART SHAPE LOVE BUCKET | D44: 2 | E44: 40485.538 | F44: 2.95 | G44: 14606 | H44: United Kingdom
A45: 493706 | B45: 84832 | C45: ZINC WILLIE WINKIE CANDLE STICK | D45: 14 | E45: 40183.606 | F45: 0.85 | G45: 15768 | H45: United Kingdom
A46: 490823 | B46: 21847 | C46: GREEN DIAMANTE PEN IN GIFT BOX | D46: 24 | E46: 40155.524 | F46: 1.25 | G46: 14841 | H46: United Kingdom
A47: 506091 | B47: 21651 | C47: HANGING GLASS ETCHED TEALIGHT | D47: 6 | E47: 40295.508 | F47: 1.65 | G47: 15402 | H47: United Kingdom
A48: 494866 | B48: 22052 | C48: VINTAGE CARAVAN GIFT WRAP | D48: 25 | E48: 40197.472 | F48: 0.42 | G48: 16253 | H48: United Kingdom
A49: 498923 | B49: 84978 | C49: HANGING HEART JAR T-LIGHT HOLDER | D49: 12 | E49: 40233.41 | F49: 1.25 | G49: 17028 | H49: United Kingdom
A50: 516157 | B50: 21069 | D50: 1 | E50: 40377.492 | F50: 1.25 | G50: 17261 | H50: United Kingdom
A51: 509100 | B51: 22511 | C51: DOORSTOP RUSSIAN DOLL RETROSPOT | D51: 1 | E51: 40318.492 | F51: 3.75 | G51: 17841 | H51: United Kingdom
A52: C511560 | B52: 20914 | C52: SET/5 RED SPOTTY LID GLASS BOWLS | D52: -1 | E52: 40338.444 | F52: 2.95 | G52: 18231 | H52: United Kingdom
A53: 524746 | B53: 22752 | C53: SET 7 BABUSHKA NESTING BOXES | D53: 4 | E53: 40451.612 | F53: 8.5 | G53: 16859 | H53: United Kingdom
A54: 496821 | B54: 22236 | C54: CAKE STAND 3 TIER MAGIC GARDEN | D54: 2 | E54: 40213.442 | F54: 12.75 | G54: 13875 | H54: United Kingdom
A55: 513964 | B55: 22380 | C55: TOY TIDY SPACEBOY | D55: 20 | E55: 40358.637 | F55: 2.1 | G55: 12380 | H55: Belgium
A56: 501291 | B56: 84578 | C56: ELEPHANT TOY WITH BLUE T-SHIRT | D56: 1 | E56: 40252.648 | F56: 3.75 | G56: 14343 | H56: United Kingdom
A57: 525944 | B57: 71477 | C57: COLOUR GLASS. STAR T-LIGHT HOLDER | D57: 5 | E57: 40458.738 | F57: 3.25 | G57: 16059 | H57: United Kingdom
A58: 498577 | B58: 21892 | C58: TRADITIONAL WOODEN CATCH CUP GAME | D58: 12 | E58: 40230.575 | F58: 1.25 | G58: 16948 | H58: United kingdom
A59: 497958 | B59: 21156 | C59: RED SPOTTY CHILDS APRON | D59: 2 | E59: 40224.556 | F59: 1.95 | G59: 14680 | H59: United Kingdom
A60: 504152 | B60: 21622 | C60: VINTAGE UNION JACK CUSHION COVER | D60: 8 | E60: 40279.576 | F60: 4.95 | G60: 17838 | H60: United Kingdom
A61: 501657 | B61: 22328 | C61: ROUND SNACK BOXES SET OF 4 FRUITS | D61: 1 | E61: 40255.549 | F61: 2.95 | G61: 13243 | H61: United Kingdom
A62: 491816 | B62: 20862 | C62: PINK PATCH PENCIL CASE BLUE HEART | D62: 6 | E62: 40161.567 | F62: 2.1 | G62: 14961 | H62: United Kingdom
A63: 493960 | B63: 22024 | C63: RAINY LADIES BIRTHDAY CARD | D63: 24 | E63: 40186.626 | F63: 0.42 | G63: 16556 | H63: United Kingdom
A64: 531746 | B64: 22745 | C64: POPPY'S PLAYHOUSE BEDROOM | D64: 1 | E64: 40491.542 | F64: 2.1 | G64: 14527 | H64: United Kingdom
A65: 512093 | B65: 21731 | C65: RED TOADSTOOL LED NIGHT LIGHT | D65: 24 | E65: 40342.546 | F65: 1.65 | G65: 16954 | H65: United Kingdom
A66: 495576 | B66: 22355 | C66: CHARLOTTE BAG , SUKI DESIGN | D66: 10 | E66: 40204.403 | F66: 0.85 | G66: 15259 | H66: United Kingdom
A67: 506383 | B67: 21431 | C67: GREEN GINGHAM FLOWER JEWELLERY BOX | D67: 8 | E67: 40297.521 | F67: 1.65 | G67: 13824 | H67: United Kingdom
A68: 523097 | B68: 48138 | C68: DOORMAT UNION FLAG | D68: 3 | E68: 40441.515 | F68: 7.95 | G68: 17055 | H68: United Kingdom
A69: 534221 | B69: 22745 | C69: POPPY'S PLAYHOUSE BEDROOM | D69: 1 | E69: 40503.677 | F69: 2.1 | G69: 16049 | H69: United Kingdom
A70: 529763 | B70: 22118 | C70: JOY WOODEN BLOCK LETTERS | D70: 1 | E70: 40480.625 | F70: 4.95 | G70: 14081 | H70: United Kingdom
A71: 528417 | B71: 22665 | C71: RECIPE BOX BLUE SKETCHBOOK DESIGN | D71: 6 | E71: 40473.4 | F71: 2.95 | G71: 14156 | H71: EIRE
A72: 510232 | B72: 22605 | C72: WOODEN CROQUET GARDEN SET | D72: 3 | E72: 40326.403 | F72: 12.75 | G72: 15674 | H72: United Kingdom
A73: 528176 | B73: 72807C | C73: SET/3 VANILLA SCENTED CANDLE IN BOX | D73: 4 | E73: 40472.436 | F73: 4.25 | G73: 12725 | H73: Italy
A74: 528761 | B74: 22435 | C74: SET OF 9 HEART SHAPED BALLOONS | D74: 12 | E74: 40475.654 | F74: 1.25 | G74: 13898 | H74: United Kingdom
A75: 501284 | B75: 22321 | C75: BIRD DECORATION RED SPOT | D75: 24 | E75: 40252.597 | F75: 0.85 | G75: 12714 | H75: France
A76: 496703 | B76: 22076 | C76: 6 RIBBONS EMPIRE | D76: 12 | E76: 40212.557 | F76: 1.65 | G76: 12396 | H76: RSA
A77: 497946 | B77: 85198 | C77: ASSORTED FARMYARD ANIMALS IN BUCKET | D77: 3312 | E77: 40224.498 | F77: 0.3 | G77: 13902 | H77: Denmark
A78: 507178 | B78: 21121 | C78: SET/10 RED SPOTTY PARTY CANDLES | D78: 288 | E78: 40304.637 | F78: 1.06 | G78: 14646 | H78: Netherlands
A79: 516265 | B79: 22378 | C79: WALL TIDY RETROSPOT | D79: 1 | E79: 40378.505 | F79: 2.1 | G79: 16782 | H79: United Kingdom
A80: 505885 | B80: 21175 | C80: GIN + TONIC DIET METAL SIGN | D80: 12 | E80: 40294.586 | F80: 2.1 | G80: 16623 | H80: United Kingdom
A81: 510139 | B81: 21892 | C81: TRADITIONAL WOODEN CATCH CUP GAME | D81: 2 | E81: 40325.517 | F81: 1.25 | G81: 16695 | H81: United Kingdom
A82: 502628 | B82: 22262 | C82: FELT EGG COSY CHICKEN | D82: 12 | E82: 40262.65 | F82: 0.85 | G82: 16670 | H82: United Kingdom
A83: 511851 | B83: 48184 | C83: DOOR MAT ENGLISH ROSE | D83: 1 | E83: 40339.806 | F83: 7.49 | G83: 13542 | H83: United Kingdom
A84: 500326 | B84: 85206A | C84: CREAM FELT EASTER EGG BASKET | D84: 2 | E84: 40244.517 | F84: 1.65 | G84: 14877 | H84: United Kingdom
A85: 526089 | B85: 22294 | C85: HEART FILIGREE DOVE SMALL | D85: 24 | E85: 40459.51 | F85: 1.25 | G85: 15281 | H85: United Kingdom
A86: 518432 | B86: 21212 | C86: PACK OF 72 RETRO SPOT CAKE CASES | D86: 24 | E86: 40399.463 | F86: 0.55 | G86: 14625 | H86: United Kingdom
A87: 533547 | B87: 84380 | C87: SET OF 3 BUTTERFLY COOKIE CUTTERS | D87: 12 | E87: 40499.7 | F87: 1.25 | G87: 16409 | H87: United Kingdom
A88: 527754 | B88: 84580 | C88: MOUSE TOY WITH PINK T-SHIRT | D88: 2 | E88: 40469.712 | F88: 3.75 | G88: 15710 | H88: United Kingdom
A89: 496008 | B89: 21428 | C89: SET3 BOOK BOX GREEN GINGHAM FLOWER | D89: 4 | E89: 40206.525 | F89: 4.25 | G89: 14911 | H89: EIRE
A90: 509071 | B90: 84839 | C90: SWEETHEART KEY CABINET | D90: 2 | E90: 40318.487 | F90: 6.75 | G90: 16471 | H90: United Kingdom
A91: 535656 | B91: 21986 | C91: PACK OF 12 PINK POLKADOT TISSUES | D91: 3 | E91: 40510.472 | F91: 0.29 | G91: 16010 | H91: united kingdom
A92: 522885 | B92: 21535 | C92: RED RETROSPOT SMALL MILK JUG | D92: 6 | E92: 40438.504 | F92: 2.55 | G92: 13952 | H92: United Kingdom
A93: 502038 | B93: 20749 | C93: ASSORTED COLOUR MINI CASES | D93: 2 | E93: 40259.576 | F93: 7.95 | G93: 13206 | H93: United Kingdom
A94: 516132 | B94: 22139 | C94: RETRO SPOT TEA SET CERAMIC 11 PC | D94: 12 | E94: 40375.644 | F94: 4.95 | G94: 16767 | H94: United Kingdom
A95: 511500 | B95: 21216 | C95: SET 3 RED SPOT TIN TEA,COFFEE,SUGAR | D95: 4 | E95: 40337.614 | F95: 4.95 | G95: 14210 | H95: United Kingdom
A96: 518547 | B96: 21426 | C96: WOODLAND STORAGE BOX SMALL | D96: 96 | E96: 40399.771 | F96: 1.25 | G96: 18102 | H96: United KIngdom
A97: 501689 | B97: 22021 | C97: BLUE FELT EASTER EGG BASKET | D97: 12 | E97: 40255.712 | F97: 1.65 | G97: 15738 | H97: United Kingdom
A98: 489802 | B98: 85104 | C98: SILVER GLASS T-LIGHT SET | D98: 4 | E98: 40149.522 | F98: 2.95 | G98: 15581 | H98: United Kingdom
A99: 497364 | B99: 84997B | C99: RED 3 PIECE MINI DOTS CUTLERY SET | D99: 6 | E99: 40218.408 | F99: 3.75 | G99: 13131 | H99: United Kingdom
A100: 535332 | B100: 84879 | C100: ASSORTED COLOUR BIRD ORNAMENT | D100: 8 | E100: 40507.663 | F100: 1.69 | G100: 18161 | H100: United Kingdom
...

Sheet Sheet2
A1: Customer ID | B1: StockCode | C1: Description | D1: Quantity | E1: Quantity | F1: Quantity | G1: Invoice | H1: InvoiceDate | I1: Price | J1: Price | K1: Invoice Date | N1: Invoice Time | O1: Country | P1: Revenue
A2: 14606 | B2: 84792 | C2: ENCHANTED BIRD COATHANGER 5 HOOK | D2: =ABS(E2) -> 4 | E2: =VALUE(F2) -> 4 | F2: 4 | G2: 503181 | H2: 40267.599 | I2: 4.65 | J2: =VALUE(I2) -> 4.65 | K2: 40267 | L2: 0.099305556 | M2: PM | N2: =TEXT(L2,"h:mm")&" "&M2 -> 2:23 PM | O2: United Kingdom | P2: =PRODUCT(D2,(J2)) -> 18.6
A3: 14911 | B3: 22318 | C3: FIVE HEART HANGING DECORATION | D3: =ABS(E3) -> 6 | E3: =VALUE(F3) -> 6 | F3: 6 | G3: 528386 | H3: 40472.772 | I3: 2.95 | J3: =VALUE(I3) -> 2.95 | K3: 40472 | L3: 0.27222222 | M3: PM | N3: =TEXT(L3,"h:mm")&" "&M3 -> 6:32 PM | O3: EIRE | P3: =PRODUCT(D3,(J3)) -> 17.7
A4: 16797 | B4: 21173 | C4: LOO ROLL METAL SIGN | D4: =ABS(E4) -> 1 | E4: =VALUE(F4) -> 1 | F4: 1 | G4: 498594 | H4: 40230.658 | I4: 1.65 | J4: =VALUE(I4) -> 1.65 | K4: 40230 | L4: 0.15833333 | M4: PM | N4: =TEXT(L4,"h:mm")&" "&M4 -> 3:48 PM | O4: United Kingdom | P4: =PRODUCT(D4,(J4)) -> 1.65
A5: 15216 | B5: 21777 | C5: RECIPE BOX WITH METAL HEART | D5: =ABS(E5) -> 2 | E5: =VALUE(F5) -> 2 | F5: 2 | G5: 503245 | H5: 40268.411 | I5: 7.95 | J5: =VALUE(I5) -> 7.95 | K5: 40268 | L5: 0.41111111 | M5: AM | N5: =TEXT(L5,"h:mm")&" "&M5 -> 9:52 AM | O5: United Kingdom | P5: =PRODUCT(D5,(J5)) -> 15.9
A6: 14677 | B6: 84836 | C6: ZINC METAL HEART DECORATION | D6: =ABS(E6) -> 12 | E6: =VALUE(F6) -> 12 | F6: 12 | G6: 505756 | H6: 40294.408 | I6: 1.25 | J6: =VALUE(I6) -> 1.25 | K6: 40294 | L6: 0.40833333 | M6: AM | N6: =TEXT(L6,"h:mm")&" "&M6 -> 9:48 AM | O6: United Kingdom | P6: =PRODUCT(D6,(J6)) -> 15
A7: 12712 | B7: 21559 | C7: STRAWBERRY LUNCHBOX WITH CUTLERY | D7: =ABS(E7) -> 6 | E7: =VALUE(F7) -> 6 | F7: 6 | G7: 496975 | H7: 40214.385 | I7: 2.55 | J7: =VALUE(I7) -> 2.55 | K7: 40214 | L7: 0.38472222 | M7: AM | N7: =TEXT(L7,"h:mm")&" "&M7 -> 9:14 AM | O7: Germany | P7: =PRODUCT(D7,(J7)) -> 15.3
A8: 12854 | B8: 85107 | C8: CUT GLASS T-LIGHT HOLDER OCTAGON | D8: =ABS(E8) -> 12 | E8: =VALUE(F8) -> 12 | F8: 12 | G8: 491584 | H8: 40158.538 | I8: 2.55 | J8: =VALUE(I8) -> 2.55 | K8: 40158 | L8: 0.53819444 | M8: PM | N8: =TEXT(L8,"h:mm")&" "&M8 -> 12:55 PM | O8: United Kingdom | P8: =PRODUCT(D8,(J8)) -> 30.6
A9: 17576 | B9: 22575 | C9: METAL MERRY CHRISTMAS WREATH | D9: =ABS(E9) -> 1 | E9: =VALUE(F9) -> 1 | F9: 1 | G9: 516478 | H9: 40379.722 | I9: 1.95 | J9: =VALUE(I9) -> 1.95 | K9: 40379 | L9: 0.22222222 | M9: PM | N9: =TEXT(L9,"h:mm")&" "&M9 -> 5:20 PM | O9: United Kingdom | P9: =PRODUCT(D9,(J9)) -> 1.95
A10: 16550 | B10: 22083 | C10: PAPER CHAIN KIT RETRO SPOT | D10: =ABS(E10) -> 2 | E10: =VALUE(F10) -> 2 | F10: 2 | G10: 502588 | H10: 40262.53 | I10: 2.95 | J10: =VALUE(I10) -> 2.95 | K10: 40262 | L10: 0.52986111 | M10: PM | N10: =TEXT(L10,"h:mm")&" "&M10 -> 12:43 PM | O10: United Kingdom | P10: =PRODUCT(D10,(J10)) -> 5.9
A11: 14606 | B11: 85014B | C11: RED/WHITE DOTS RUFFLED UMBRELLA | D11: =ABS(E11) -> 1 | E11: =VALUE(F11) -> 1 | F11: 1 | G11: 515335 | H11: 40370.597 | I11: 5.95 | J11: =VALUE(I11) -> 5.95 | K11: 40370 | L11: 0.096527778 | M11: PM | N11: =TEXT(L11,"h:mm")&" "&M11 -> 2:19 PM | O11: United Kingdom | P11: =PRODUCT(D11,(J11)) -> 5.95
A12: 16799 | B12: 21156 | C12: RETROSPOT CHILDRENS APRON | D12: =ABS(E12) -> 1 | E12: =VALUE(F12) -> 1 | F12: 1 | G12: 525065 | H12: 40454.603 | I12: 1.95 | J12: =VALUE(I12) -> 1.95 | K12: 40454 | L12: 0.10277778 | M12: PM | N12: =TEXT(L12,"h:mm")&" "&M12 -> 2:28 PM | O12: United Kingdom | P12: =PRODUCT(D12,(J12)) -> 1.95
A13: 18245 | B13: 84946 | C13: ANTIQUE SILVER TEA GLASS ETCHED | D13: =ABS(E13) -> 24 | E13: =VALUE(F13) -> 24 | F13: 24 | G13: 535349 | H13: 40507.703 | I13: 1.25 | J13: =VALUE(I13) -> 1.25 | K13: 40507 | L13: 0.20277778 | M13: PM | N13: =TEXT(L13,"h:mm")&" "&M13 -> 4:52 PM | O13: United Kingdom | P13: =PRODUCT(D13,(J13)) -> 30
A14: 15150 | B14: 82484 | C14: WOOD BLACK BOARD ANT WHITE FINISH | D14: =ABS(E14) -> 3 | E14: =VALUE(F14) -> 3 | F14: 3 | G14: 521949 | H14: 40430.719 | I14: 6.45 | J14: =VALUE(I14) -> 6.45 | K14: 40430 | L14: 0.21944444 | M14: PM | N14: =TEXT(L14,"h:mm")&" "&M14 -> 5:16 PM | O14: United Kingdom | P14: =PRODUCT(D14,(J14)) -> 19.35
A15: 17511 | B15: 22519 | C15: CHILDS GARDEN BRUSH PINK | D15: =ABS(E15) -> 36 | E15: =VALUE(F15) -> 36 | F15: 36 | G15: 514876 | H15: 40366.44 | I15: 1.85 | J15: =VALUE(I15) -> 1.85 | K15: 40366 | L15: 0.43958333 | M15: AM | N15: =TEXT(L15,"h:mm")&" "&M15 -> 10:33 AM | O15: United Kingdom | P15: =PRODUCT(D15,(J15)) -> 66.6
A16: 12598 | B16: 22561 | C16: WOODEN SCHOOL COLOURING SET | D16: =ABS(E16) -> 12 | E16: =VALUE(F16) -> 12 | F16: 12 | G16: 521162 | H16: 40423.599 | I16: 1.65 | J16: =VALUE(I16) -> 1.65 | K16: 40423 | L16: 0.098611111 | M16: PM | N16: =TEXT(L16,"h:mm")&" "&M16 -> 2:22 PM | O16: France | P16: =PRODUCT(D16,(J16)) -> 19.8
A17: 16374 | B17: 20798 | C17: CLEAR MILKSHAKE GLASS | D17: =ABS(E17) -> 4 | E17: =VALUE(F17) -> 4 | F17: 4 | G17: 506572 | H17: 40298.549 | I17: 2.1 | J17: =VALUE(I17) -> 2.1 | K17: 40298 | L17: 0.048611111 | M17: PM | N17: =TEXT(L17,"h:mm")&" "&M17 -> 1:10 PM | O17: United Kingdom | P17: =PRODUCT(D17,(J17)) -> 8.4
A18: 17449 | B18: 48188 | C18: DOOR MAT WELCOME PUPPIES | D18: =ABS(E18) -> 1 | E18: =VALUE(F18) -> 1 | F18: 1 | G18: 505974 | H18: 40294.754 | I18: 7.49 | J18: =VALUE(I18) -> 7.49 | K18: 40294 | L18: 0.25416667 | M18: PM | N18: =TEXT(L18,"h:mm")&" "&M18 -> 6:06 PM | O18: United Kingdom | P18: =PRODUCT(D18,(J18)) -> 7.49
A19: 13415 | B19: 10125 | C19: MINI FUNKY DESIGN TAPES | D19: =ABS(E19) -> 1 | E19: =VALUE(F19) -> 1 | F19: 1 | G19: 491622 | H19: 40158.597 | I19: 0.85 | J19: =VALUE(I19) -> 0.85 | K19: 40158 | L19: 0.097222222 | M19: PM | N19: =TEXT(L19,"h:mm")&" "&M19 -> 2:20 PM | O19: United Kingdom | P19: =PRODUCT(D19,(J19)) -> 0.85
A20: 12924 | B20: 21696 | C20: SMALL SILVER TRELLIS CANDLEPOT | D20: =ABS(E20) -> 6 | E20: =VALUE(F20) -> 6 | F20: 6 | G20: 509982 | H20: 40324.603 | I20: 2.95 | J20: =VALUE(I20) -> 2.95 | K20: 40324 | L20: 0.10277778 | M20: PM | N20: =TEXT(L20,"h:mm")&" "&M20 -> 2:28 PM | O20: United Kingdom | P20: =PRODUCT(D20,(J20)) -> 17.7
A21: 13078 | B21: 85114B | C21: IVORY ENCHANTED FOREST PLACEMAT | D21: =ABS(E21) -> 6 | E21: =VALUE(F21) -> 6 | F21: 6 | G21: 524611 | H21: 40451.401 | I21: 1.65 | J21: =VALUE(I21) -> 1.65 | K21: 40451 | L21: 0.40069444 | M21: AM | N21: =TEXT(L21,"h:mm")&" "&M21 -> 9:37 AM | O21: United Kingdom | P21: =PRODUCT(D21,(J21)) -> 9.9
A22: 17340 | B22: 22413 | C22: METAL SIGN TAKE IT OR LEAVE IT | D22: =ABS(E22) -> 12 | E22: =VALUE(F22) -> 12 | F22: 12 | G22: 501906 | H22: 40258.668 | I22: 2.95 | J22: =VALUE(I22) -> 2.95 | K22: 40258 | L22: 0.16805556 | M22: PM | N22: =TEXT(L22,"h:mm")&" "&M22 -> 4:02 PM | O22: United Kingdom | P22: =PRODUCT(D22,(J22)) -> 35.4
A23: 13782 | B23: 20979 | C23: 36 PENCILS TUBE RED SPOTTY | D23: =ABS(E23) -> 1 | E23: =VALUE(F23) -> 1 | F23: 1 | G23: 505708 | H23: 40293.51 | I23: 1.25 | J23: =VALUE(I23) -> 1.25 | K23: 40293 | L23: 0.51041667 | M23: PM | N23: =TEXT(L23,"h:mm")&" "&M23 -> 12:15 PM | O23: United Kingdom | P23: =PRODUCT(D23,(J23)) -> 1.25
A24: 13408 | B24: 79323W | C24: WHITE CHERRY LIGHTS | D24: =ABS(E24) -> 24 | E24: =VALUE(F24) -> 24 | F24: 24 | G24: 497935 | H24: 40224.449 | I24: 5.45 | J24: =VALUE(I24) -> 5.45 | K24: 40224 | L24: 0.44930556 | M24: AM | N24: =TEXT(L24,"h:mm")&" "&M24 -> 10:47 AM | O24: United Kingdom | P24: =PRODUCT(D24,(J24)) -> 130.8
A25: 14253 | B25: 15044C | C25: PURPLE PAPER PARASOL | D25: =ABS(E25) -> 6 | E25: =VALUE(F25) -> 6 | F25: 6 | G25: 502792 | H25: 40263.631 | I25: 2.95 | J25: =VALUE(I25) -> 2.95 | K25: 40263 | L25: 0.13055556 | M25: PM | N25: =TEXT(L25,"h:mm")&" "&M25 -> 3:08 PM | O25: United Kingdom | P25: =PRODUCT(D25,(J25)) -> 17.7
A26: 12744 | B26: 21179 | C26: N/A | D26: =ABS(E26) -> 12 | E26: =VALUE(F26) -> 12 | F26: 12 | G26: 521403 | H26: 40427.43 | I26: 1.25 | J26: =VALUE(I26) -> 1.25 | K26: 40427 | L26: 0.42986111 | M26: AM | N26: =TEXT(L26,"h:mm")&" "&M26 -> 10:19 AM | O26: Singapore | P26: =PRODUCT(D26,(J26)) -> 15
A27: 17765 | B27: 72529W | C27: WHITE ADVENT CANDLE | D27: =ABS(E27) -> 1 | E27: =VALUE(F27) -> 1 | F27: 1 | G27: 522904 | H27: 40438.531 | I27: 2.12 | J27: =VALUE(I27) -> 2.12 | K27: 40438 | L27: 0.53125 | M27: PM | N27: =TEXT(L27,"h:mm")&" "&M27 -> 12:45 PM | O27: United Kingdom | P27: =PRODUCT(D27,(J27)) -> 2.12
A28: 15032 | B28: 22415 | C28: WHITE TISSUE REAM | D28: =ABS(E28) -> 3 | E28: =VALUE(F28) -> 3 | F28: 3 | G28: 537810 | H28: 08-12-2010 13:30 | I28: 7.95 | J28: =VALUE(I28) -> 7.95 | K28: 40402 | L28: 0.5625 | N28: =TEXT(L28,"h:mm")&" "&M28 -> 13:30 | O28: United Kingdom | P28: =PRODUCT(D28,(J28)) -> 23.85
A29: 17663 | B29: 21258 | C29: VICTORIAN SEWING BOX LARGE | D29: =ABS(E29) -> 1 | E29: =VALUE(F29) -> 1 | F29: 1 | G29: 520505 | H29: 40416.535 | I29: 12.75 | J29: =VALUE(I29) -> 12.75 | K29: 40416 | L29: 0.53541667 | M29: PM | N29: =TEXT(L29,"h:mm")&" "&M29 -> 12:51 PM | O29: United Kingdom | P29: =PRODUCT(D29,(J29)) -> 12.75
A30: 17284 | B30: 21122 | C30: SET/10 PINK POLKADOT PARTY CANDLES | D30: =ABS(E30) -> 24 | E30: =VALUE(F30) -> 24 | F30: 24 | G30: 533067 | H30: 40497.718 | I30: 1.25 | J30: =VALUE(I30) -> 1.25 | K30: 40497 | L30: 0.21805556 | M30: PM | N30: =TEXT(L30,"h:mm")&" "&M30 -> 5:14 PM | O30: United Kingdom | P30: =PRODUCT(D30,(J30)) -> 30
A31: 15967 | B31: 21009 | C31: ETCHED GLASS STAR TREE DECORATION | D31: =ABS(E31) -> 6 | E31: =VALUE(F31) -> 6 | F31: 6 | G31: 523971 | H31: 40447.578 | I31: 1.25 | J31: =VALUE(I31) -> 1.25 | K31: 40447 | L31: 0.078472222 | M31: PM | N31: =TEXT(L31,"h:mm")&" "&M31 -> 1:53 PM | O31: United Kingdom | P31: =PRODUCT(D31,(J31)) -> 7.5
A32: 17965 | B32: 15056BL | C32: EDWARDIAN PARASOL BLACK | D32: =ABS(E32) -> 2 | E32: =VALUE(F32) -> 2 | F32: 2 | G32: 499625 | H32: 40238.551 | I32: 5.95 | J32: =VALUE(I32) -> 5.95 | K32: 40238 | L32: 0.051388889 | M32: PM | N32: =TEXT(L32,"h:mm")&" "&M32 -> 1:14 PM | O32: United Kingdom | P32: =PRODUCT(D32,(J32)) -> 11.9
A33: 15812 | B33: 47566 | C33: PARTY BUNTING | D33: =ABS(E33) -> 8 | E33: =VALUE(F33) -> 8 | F33: 8 | G33: 500147 | H33: 40241.724 | I33: 4.65 | J33: =VALUE(I33) -> 4.65 | K33: 40241 | L33: 0.22361111 | M33: PM | N33: =TEXT(L33,"h:mm")&" "&M33 -> 5:22 PM | O33: United Kingdom | P33: =PRODUCT(D33,(J33)) -> 37.2
A34: 17218 | B34: 22569 | C34: FELTCRAFT CUSHION BUTTERFLY | D34: =ABS(E34) -> 2 | E34: =VALUE(F34) -> 2 | F34: 2 | G34: 537421 | H34: 40518.642 | I34: 3.75 | J34: =VALUE(I34) -> 3.75 | K34: 40518 | L34: 0.14236111 | M34: PM | N34: =TEXT(L34,"h:mm")&" "&M34 -> 3:25 PM | O34: United Kingdom | P34: =PRODUCT(D34,(J34)) -> 7.5
A35: 15384 | B35: 21930 | C35: JUMBO STORAGE BAG SKULLS | D35: =ABS(E35) -> 10 | E35: =VALUE(F35) -> 10 | F35: 10 | G35: 534526 | H35: 40505.503 | I35: 1.95 | J35: =VALUE(I35) -> 1.95 | K35: 40505 | L35: 0.50277778 | M35: PM | N35: =TEXT(L35,"h:mm")&" "&M35 -> 12:04 PM | O35: United Kingdom | P35: =PRODUCT(D35,(J35)) -> 19.5
A36: 17464 | B36: 22556 | C36: PLASTERS IN TIN CIRCUS PARADE | D36: =ABS(E36) -> 1 | E36: =VALUE(F36) -> 1 | F36: 1 | G36: 503164 | H36: 40267.552 | I36: 1.65 | J36: =VALUE(I36) -> 1.65 | K36: 40267 | L36: 0.052083333 | M36: PM | N36: =TEXT(L36,"h:mm")&" "&M36 -> 1:15 PM | O36: United Kingdom | P36: =PRODUCT(D36,(J36)) -> 1.65
A37: 13263 | B37: 21499 | C37: BLUE POLKADOT WRAP | D37: =ABS(E37) -> 25 | E37: =VALUE(F37) -> 25 | F37: 25 | G37: 528618 | H37: 40473.713 | I37: 0.42 | J37: =VALUE(I37) -> 0.42 | K37: 40473 | L37: 0.21319444 | M37: PM | N37: =TEXT(L37,"h:mm")&" "&M37 -> 5:07 PM | O37: United Kingdom | P37: =PRODUCT(D37,(J37)) -> 10.5
A38: 14156 | B38: 22196 | C38: SMALL HEART MEASURING SPOONS | D38: =ABS(E38) -> 12 | E38: =VALUE(F38) -> 12 | F38: 12 | G38: 505015 | H38: 40287.562 | I38: 0.85 | J38: =VALUE(I38) -> 0.85 | K38: 40287 | L38: 0.0625 | M38: PM | N38: =TEXT(L38,"h:mm")&" "&M38 -> 1:30 PM | O38: EIRE | P38: =PRODUCT(D38,(J38)) -> 10.2
A39: 17160 | B39: 84510B | C39: SET OF 4 FAIRY CAKES COASTERS | D39: =ABS(E39) -> 10 | E39: =VALUE(F39) -> 10 | F39: 10 | G39: 497272 | H39: 40217.576 | I39: 1.25 | J39: =VALUE(I39) -> 1.25 | K39: 40217 | L39: 0.076388889 | M39: PM | N39: =TEXT(L39,"h:mm")&" "&M39 -> 1:50 PM | O39: United Kingdom | P39: =PRODUCT(D39,(J39)) -> 12.5
A40: 16470 | B40: 21890 | C40: S/6 WOODEN SKITTLES IN COTTON BAG | D40: =ABS(E40) -> 2 | E40: =VALUE(F40) -> 2 | F40: 2 | G40: 518480 | H40: 40399.515 | I40: 2.95 | J40: =VALUE(I40) -> 2.95 | K40: 40399 | L40: 0.51458333 | M40: PM | N40: =TEXT(L40,"h:mm")&" "&M40 -> 12:21 PM | O40: United Kingdom | P40: =PRODUCT(D40,(J40)) -> 5.9
A41: 13488 | B41: 21900 | C41: KEY FOB , SHED | D41: =ABS(E41) -> 24 | E41: =VALUE(F41) -> 24 | F41: 24 | G41: 508593 | H41: 40315.504 | I41: 0.65 | J41: =VALUE(I41) -> 0.65 | K41: 40315 | L41: 0.50416667 | M41: PM | N41: =TEXT(L41,"h:mm")&" "&M41 -> 12:06 PM | O41: United Kingdom | P41: =PRODUCT(D41,(J41)) -> 15.6
A42: 15288 | B42: 20712 | C42: JUMBO BAG WOODLAND ANIMALS | D42: =ABS(E42) -> 10 | E42: =VALUE(F42) -> 10 | F42: 10 | G42: 505615 | H42: 40291.534 | I42: 1.95 | J42: =VALUE(I42) -> 1.95 | K42: 40291 | L42: 0.53402778 | M42: PM | N42: =TEXT(L42,"h:mm")&" "&M42 -> 12:49 PM | O42: United Kingdom | P42: =PRODUCT(D42,(J42)) -> 19.5
A43: 14606 | B43: 22551 | C43: PLASTERS IN TIN SPACEBOY | D43: =ABS(E43) -> 1 | E43: =VALUE(F43) -> 1 | F43: 1 | G43: 523314 | H43: 40442.558 | I43: 1.65 | J43: =VALUE(I43) -> 1.65 | K43: 40442 | L43: 0.058333333 | M43: PM | N43: =TEXT(L43,"h:mm")&" "&M43 -> 1:24 PM | O43: United Kingdom | P43: =PRODUCT(D43,(J43)) -> 1.65
A44: 14606 | B44: 21563 | C44: RED HEART SHAPE LOVE BUCKET | D44: =ABS(E44) -> 2 | E44: =VALUE(F44) -> 2 | F44: 2 | G44: 530538 | H44: 40485.538 | I44: 2.95 | J44: =VALUE(I44) -> 2.95 | K44: 40485 | L44: 0.53819444 | M44: PM | N44: =TEXT(L44,"h:mm")&" "&M44 -> 12:55 PM | O44: United Kingdom | P44: =PRODUCT(D44,(J44)) -> 5.9
A45: 15768 | B45: 84832 | C45: ZINC WILLIE WINKIE CANDLE STICK | D45: =ABS(E45) -> 14 | E45: =VALUE(F45) -> 14 | F45: 14 | G45: 493706 | H45: 40183.606 | I45: 0.85 | J45: =VALUE(I45) -> 0.85 | K45: 40183 | L45: 0.10555556 | M45: PM | N45: =TEXT(L45,"h:mm")&" "&M45 -> 2:32 PM | O45: United Kingdom | P45: =PRODUCT(D45,(J45)) -> 11.9
A46: 14841 | B46: 21847 | C46: GREEN DIAMANTE PEN IN GIFT BOX | D46: =ABS(E46) -> 24 | E46: =VALUE(F46) -> 24 | F46: 24 | G46: 490823 | H46: 40155.524 | I46: 1.25 | J46: =VALUE(I46) -> 1.25 | K46: 40155 | L46: 0.52361111 | M46: PM | N46: =TEXT(L46,"h:mm")&" "&M46 -> 12:34 PM | O46: United Kingdom | P46: =PRODUCT(D46,(J46)) -> 30
A47: 15402 | B47: 21651 | C47: HANGING GLASS ETCHED TEALIGHT | D47: =ABS(E47) -> 6 | E47: =VALUE(F47) -> 6 | F47: 6 | G47: 506091 | H47: 40295.508 | I47: 1.65 | J47: =VALUE(I47) -> 1.65 | K47: 40295 | L47: 0.50833333 | M47: PM | N47: =TEXT(L47,"h:mm")&" "&M47 -> 12:12 PM | O47: United Kingdom | P47: =PRODUCT(D47,(J47)) -> 9.9
A48: 16253 | B48: 22052 | C48: VINTAGE CARAVAN GIFT WRAP | D48: =ABS(E48) -> 25 | E48: =VALUE(F48) -> 25 | F48: 25 | G48: 494866 | H48: 40197.472 | I48: 0.42 | J48: =VALUE(I48) -> 0.42 | K48: 40197 | L48: 0.47222222 | M48: AM | N48: =TEXT(L48,"h:mm")&" "&M48 -> 11:20 AM | O48: United Kingdom | P48: =PRODUCT(D48,(J48)) -> 10.5
A49: 17028 | B49: 84978 | C49: HANGING HEART JAR T-LIGHT HOLDER | D49: =ABS(E49) -> 12 | E49: =VALUE(F49) -> 12 | F49: 12 | G49: 498923 | H49: 40233.41 | I49: 1.25 | J49: =VALUE(I49) -> 1.25 | K49: 40233 | L49: 0.40972222 | M49: AM | N49: =TEXT(L49,"h:mm")&" "&M49 -> 9:50 AM | O49: United Kingdom | P49: =PRODUCT(D49,(J49)) -> 15
A50: 17261 | B50: 21069 | C50: N/A | D50: =ABS(E50) -> 1 | E50: =VALUE(F50) -> 1 | F50: 1 | G50: 516157 | H50: 40377.492 | I50: 1.25 | J50: =VALUE(I50) -> 1.25 | K50: 40377 | L50: 0.49236111 | M50: AM | N50: =TEXT(L50,"h:mm")&" "&M50 -> 11:49 AM | O50: United Kingdom | P50: =PRODUCT(D50,(J50)) -> 1.25
A51: 17841 | B51: 22511 | C51: DOORSTOP RUSSIAN DOLL RETROSPOT | D51: =ABS(E51) -> 1 | E51: =VALUE(F51) -> 1 | F51: 1 | G51: 509100 | H51: 40318.492 | I51: 3.75 | J51: =VALUE(I51) -> 3.75 | K51: 40318 | L51: 0.49236111 | M51: AM | N51: =TEXT(L51,"h:mm")&" "&M51 -> 11:49 AM | O51: United Kingdom | P51: =PRODUCT(D51,(J51)) -> 3.75
A52: 18231 | B52: 20914 | C52: SET/5 RED SPOTTY LID GLASS BOWLS | D52: =ABS(E52) -> 1 | E52: =VALUE(F52) -> -1 | F52: -1 | G52: C511560 | H52: 40338.444 | I52: 2.95 | J52: =VALUE(I52) -> 2.95 | K52: 40338 | L52: 0.44375 | M52: AM | N52: =TEXT(L52,"h:mm")&" "&M52 -> 10:39 AM | O52: United Kingdom | P52: =PRODUCT(D52,(J52)) -> 2.95
A53: 16859 | B53: 22752 | C53: SET 7 BABUSHKA NESTING BOXES | D53: =ABS(E53) -> 4 | E53: =VALUE(F53) -> 4 | F53: 4 | G53: 524746 | H53: 40451.612 | I53: 8.5 | J53: =VALUE(I53) -> 8.5 | K53: 40451 | L53: 0.11180556 | M53: PM | N53: =TEXT(L53,"h:mm")&" "&M53 -> 2:41 PM | O53: United Kingdom | P53: =PRODUCT(D53,(J53)) -> 34
A54: 13875 | B54: 22236 | C54: CAKE STAND 3 TIER MAGIC GARDEN | D54: =ABS(E54) -> 2 | E54: =VALUE(F54) -> 2 | F54: 2 | G54: 496821 | H54: 40213.442 | I54: 12.75 | J54: =VALUE(I54) -> 12.75 | K54: 40213 | L54: 0.44236111 | M54: AM | N54: =TEXT(L54,"h:mm")&" "&M54 -> 10:37 AM | O54: United Kingdom | P54: =PRODUCT(D54,(J54)) -> 25.5
A55: 12380 | B55: 22380 | C55: TOY TIDY SPACEBOY | D55: =ABS(E55) -> 20 | E55: =VALUE(F55) -> 20 | F55: 20 | G55: 513964 | H55: 40358.637 | I55: 2.1 | J55: =VALUE(I55) -> 2.1 | K55: 40358 | L55: 0.13680556 | M55: PM | N55: =TEXT(L55,"h:mm")&" "&M55 -> 3:17 PM | O55: Belgium | P55: =PRODUCT(D55,(J55)) -> 42
A56: 14343 | B56: 84578 | C56: ELEPHANT TOY WITH BLUE T-SHIRT | D56: =ABS(E56) -> 1 | E56: =VALUE(F56) -> 1 | F56: 1 | G56: 501291 | H56: 40252.648 | I56: 3.75 | J56: =VALUE(I56) -> 3.75 | K56: 40252 | L56: 0.14791667 | M56: PM | N56: =TEXT(L56,"h:mm")&" "&M56 -> 3:33 PM | O56: United Kingdom | P56: =PRODUCT(D56,(J56)) -> 3.75
A57: 16059 | B57: 71477 | C57: COLOUR GLASS. STAR T-LIGHT HOLDER | D57: =ABS(E57) -> 5 | E57: =VALUE(F57) -> 5 | F57: 5 | G57: 525944 | H57: 40458.738 | I57: 3.25 | J57: =VALUE(I57) -> 3.25 | K57: 40458 | L57: 0.2375 | M57: PM | N57: =TEXT(L57,"h:mm")&" "&M57 -> 5:42 PM | O57: United Kingdom | P57: =PRODUCT(D57,(J57)) -> 16.25
A58: 16948 | B58: 21892 | C58: TRADITIONAL WOODEN CATCH CUP GAME | D58: =ABS(E58) -> 12 | E58: =VALUE(F58) -> 12 | F58: 12 | G58: 498577 | H58: 40230.575 | I58: 1.25 | J58: =VALUE(I58) -> 1.25 | K58: 40230 | L58: 0.075 | M58: PM | N58: =TEXT(L58,"h:mm")&" "&M58 -> 1:48 PM | O58: United Kingdom | P58: =PRODUCT(D58,(J58)) -> 15
A59: 14680 | B59: 21156 | C59: RED SPOTTY CHILDS APRON | D59: =ABS(E59) -> 2 | E59: =VALUE(F59) -> 2 | F59: 2 | G59: 497958 | H59: 40224.556 | I59: 1.95 | J59: =VALUE(I59) -> 1.95 | K59: 40224 | L59: 0.055555556 | M59: PM | N59: =TEXT(L59,"h:mm")&" "&M59 -> 1:20 PM | O59: United Kingdom | P59: =PRODUCT(D59,(J59)) -> 3.9
A60: 17838 | B60: 21622 | C60: VINTAGE UNION JACK CUSHION COVER | D60: =ABS(E60) -> 8 | E60: =VALUE(F60) -> 8 | F60: 8 | G60: 504152 | H60: 40279.576 | I60: 4.95 | J60: =VALUE(I60) -> 4.95 | K60: 40279 | L60: 0.075694444 | M60: PM | N60: =TEXT(L60,"h:mm")&" "&M60 -> 1:49 PM | O60: United Kingdom | P60: =PRODUCT(D60,(J60)) -> 39.6
A61: 13243 | B61: 22328 | C61: ROUND SNACK BOXES SET OF 4 FRUITS | D61: =ABS(E61) -> 1 | E61: =VALUE(F61) -> 1 | F61: 1 | G61: 501657 | H61: 40255.549 | I61: 2.95 | J61: =VALUE(I61) -> 2.95 | K61: 40255 | L61: 0.048611111 | M61: PM | N61: =TEXT(L61,"h:mm")&" "&M61 -> 1:10 PM | O61: United Kingdom | P61: =PRODUCT(D61,(J61)) -> 2.95
A62: 14961 | B62: 20862 | C62: PINK PATCH PENCIL CASE BLUE HEART | D62: =ABS(E62) -> 6 | E62: =VALUE(F62) -> 6 | F62: 6 | G62: 491816 | H62: 40161.567 | I62: 2.1 | J62: =VALUE(I62) -> 2.1 | K62: 40161 | L62: 0.066666667 | M62: PM | N62: =TEXT(L62,"h:mm")&" "&M62 -> 1:36 PM | O62: United Kingdom | P62: =PRODUCT(D62,(J62)) -> 12.6
A63: 16556 | B63: 22024 | C63: RAINY LADIES BIRTHDAY CARD | D63: =ABS(E63) -> 24 | E63: =VALUE(F63) -> 24 | F63: 24 | G63: 493960 | H63: 40186.626 | I63: 0.42 | J63: =VALUE(I63) -> 0.42 | K63: 40186 | L63: 0.12569444 | M63: PM | N63: =TEXT(L63,"h:mm")&" "&M63 -> 3:01 PM | O63: United Kingdom | P63: =PRODUCT(D63,(J63)) -> 10.08
A64: 14527 | B64: 22745 | C64: POPPY'S PLAYHOUSE BEDROOM | D64: =ABS(E64) -> 1 | E64: =VALUE(F64) -> 1 | F64: 1 | G64: 531746 | H64: 40491.542 | I64: 2.1 | J64: =VALUE(I64) -> 2.1 | K64: 40491 | L64: 0.041666667 | M64: PM | N64: =TEXT(L64,"h:mm")&" "&M64 -> 1:00 PM | O64: United Kingdom | P64: =PRODUCT(D64,(J64)) -> 2.1
A65: 16954 | B65: 21731 | C65: RED TOADSTOOL LED NIGHT LIGHT | D65: =ABS(E65) -> 24 | E65: =VALUE(F65) -> 24 | F65: 24 | G65: 512093 | H65: 40342.546 | I65: 1.65 | J65: =VALUE(I65) -> 1.65 | K65: 40342 | L65: 0.045833333 | M65: PM | N65: =TEXT(L65,"h:mm")&" "&M65 -> 1:06 PM | O65: United Kingdom | P65: =PRODUCT(D65,(J65)) -> 39.6
A66: 15259 | B66: 22355 | C66: CHARLOTTE BAG , SUKI DESIGN | D66: =ABS(E66) -> 10 | E66: =VALUE(F66) -> 10 | F66: 10 | G66: 495576 | H66: 40204.403 | I66: 0.85 | J66: =VALUE(I66) -> 0.85 | K66: 40204 | L66: 0.40347222 | M66: AM | N66: =TEXT(L66,"h:mm")&" "&M66 -> 9:41 AM | O66: United Kingdom | P66: =PRODUCT(D66,(J66)) -> 8.5
A67: 13824 | B67: 21431 | C67: GREEN GINGHAM FLOWER JEWELLERY BOX | D67: =ABS(E67) -> 8 | E67: =VALUE(F67) -> 8 | F67: 8 | G67: 506383 | H67: 40297.521 | I67: 1.65 | J67: =VALUE(I67) -> 1.65 | K67: 40297 | L67: 0.52083333 | M67: PM | N67: =TEXT(L67,"h:mm")&" "&M67 -> 12:30 PM | O67: United Kingdom | P67: =PRODUCT(D67,(J67)) -> 13.2
A68: 17055 | B68: 48138 | C68: DOORMAT UNION FLAG | D68: =ABS(E68) -> 3 | E68: =VALUE(F68) -> 3 | F68: 3 | G68: 523097 | H68: 40441.515 | I68: 7.95 | J68: =VALUE(I68) -> 7.95 | K68: 40441 | L68: 0.51458333 | M68: PM | N68: =TEXT(L68,"h:mm")&" "&M68 -> 12:21 PM | O68: United Kingdom | P68: =PRODUCT(D68,(J68)) -> 23.85
A69: 16049 | B69: 22745 | C69: POPPY'S PLAYHOUSE BEDROOM | D69: =ABS(E69) -> 1 | E69: =VALUE(F69) -> 1 | F69: 1 | G69: 534221 | H69: 40503.677 | I69: 2.1 | J69: =VALUE(I69) -> 2.1 | K69: 40503 | L69: 0.17708333 | M69: PM | N69: =TEXT(L69,"h:mm")&" "&M69 -> 4:15 PM | O69: United Kingdom | P69: =PRODUCT(D69,(J69)) -> 2.1
A70: 14081 | B70: 22118 | C70: JOY WOODEN BLOCK LETTERS | D70: =ABS(E70) -> 1 | E70: =VALUE(F70) -> 1 | F70: 1 | G70: 529763 | H70: 40480.625 | I70: 4.95 | J70: =VALUE(I70) -> 4.95 | K70: 40480 | L70: 0.125 | M70: PM | N70: =TEXT(L70,"h:mm")&" "&M70 -> 3:00 PM | O70: United Kingdom | P70: =PRODUCT(D70,(J70)) -> 4.95
A71: 14156 | B71: 22665 | C71: RECIPE BOX BLUE SKETCHBOOK DESIGN | D71: =ABS(E71) -> 6 | E71: =VALUE(F71) -> 6 | F71: 6 | G71: 528417 | H71: 40473.4 | I71: 2.95 | J71: =VALUE(I71) -> 2.95 | K71: 40473 | L71: 0.4 | M71: AM | N71: =TEXT(L71,"h:mm")&" "&M71 -> 9:36 AM | O71: EIRE | P71: =PRODUCT(D71,(J71)) -> 17.7
A72: 15674 | B72: 22605 | C72: WOODEN CROQUET GARDEN SET | D72: =ABS(E72) -> 3 | E72: =VALUE(F72) -> 3 | F72: 3 | G72: 510232 | H72: 40326.403 | I72: 12.75 | J72: =VALUE(I72) -> 12.75 | K72: 40326 | L72: 0.40277778 | M72: AM | N72: =TEXT(L72,"h:mm")&" "&M72 -> 9:40 AM | O72: United Kingdom | P72: =PRODUCT(D72,(J72)) -> 38.25
A73: 12725 | B73: 72807C | C73: SET/3 VANILLA SCENTED CANDLE IN BOX | D73: =ABS(E73) -> 4 | E73: =VALUE(F73) -> 4 | F73: 4 | G73: 528176 | H73: 40472.436 | I73: 4.25 | J73: =VALUE(I73) -> 4.25 | K73: 40472 | L73: 0.43611111 | M73: AM | N73: =TEXT(L73,"h:mm")&" "&M73 -> 10:28 AM | O73: Italy | P73: =PRODUCT(D73,(J73)) -> 17
A74: 13898 | B74: 22435 | C74: SET OF 9 HEART SHAPED BALLOONS | D74: =ABS(E74) -> 12 | E74: =VALUE(F74) -> 12 | F74: 12 | G74: 528761 | H74: 40475.654 | I74: 1.25 | J74: =VALUE(I74) -> 1.25 | K74: 40475 | L74: 0.15416667 | M74: PM | N74: =TEXT(L74,"h:mm")&" "&M74 -> 3:42 PM | O74: United Kingdom | P74: =PRODUCT(D74,(J74)) -> 15
A75: 12714 | B75: 22321 | C75: BIRD DECORATION RED SPOT | D75: =ABS(E75) -> 24 | E75: =VALUE(F75) -> 24 | F75: 24 | G75: 501284 | H75: 40252.597 | I75: 0.85 | J75: =VALUE(I75) -> 0.85 | K75: 40252 | L75: 0.096527778 | M75: PM | N75: =TEXT(L75,"h:mm")&" "&M75 -> 2:19 PM | O75: France | P75: =PRODUCT(D75,(J75)) -> 20.4
A76: 12396 | B76: 22076 | C76: 6 RIBBONS EMPIRE | D76: =ABS(E76) -> 12 | E76: =VALUE(F76) -> 12 | F76: 12 | G76: 496703 | H76: 40212.557 | I76: 1.65 | J76: =VALUE(I76) -> 1.65 | K76: 40212 | L76: 0.056944444 | M76: PM | N76: =TEXT(L76,"h:mm")&" "&M76 -> 1:22 PM | O76: RSA | P76: =PRODUCT(D76,(J76)) -> 19.8
A77: 13902 | B77: 85198 | C77: ASSORTED FARMYARD ANIMALS IN BUCKET | D77: =ABS(E77) -> 3312 | E77: =VALUE(F77) -> 3312 | F77: 3312 | G77: 497946 | H77: 40224.498 | I77: 0.3 | J77: =VALUE(I77) -> 0.3 | K77: 40224 | L77: 0.49791667 | M77: AM | N77: =TEXT(L77,"h:mm")&" "&M77 -> 11:57 AM | O77: Denmark | P77: =PRODUCT(D77,(J77)) -> 993.6
A78: 14646 | B78: 21121 | C78: SET/10 RED SPOTTY PARTY CANDLES | D78: =ABS(E78) -> 288 | E78: =VALUE(F78) -> 288 | F78: 288 | G78: 507178 | H78: 40304.637 | I78: 1.06 | J78: =VALUE(I78) -> 1.06 | K78: 40304 | L78: 0.13680556 | M78: PM | N78: =TEXT(L78,"h:mm")&" "&M78 -> 3:17 PM | O78: Netherlands | P78: =PRODUCT(D78,(J78)) -> 305.28
A79: 16782 | B79: 22378 | C79: WALL TIDY RETROSPOT | D79: =ABS(E79) -> 1 | E79: =VALUE(F79) -> 1 | F79: 1 | G79: 516265 | H79: 40378.505 | I79: 2.1 | J79: =VALUE(I79) -> 2.1 | K79: 40378 | L79: 0.50486111 | M79: PM | N79: =TEXT(L79,"h:mm")&" "&M79 -> 12:07 PM | O79: United Kingdom | P79: =PRODUCT(D79,(J79)) -> 2.1
A80: 16623 | B80: 21175 | C80: GIN + TONIC DIET METAL SIGN | D80: =ABS(E80) -> 12 | E80: =VALUE(F80) -> 12 | F80: 12 | G80: 505885 | H80: 40294.586 | I80: 2.1 | J80: =VALUE(I80) -> 2.1 | K80: 40294 | L80: 0.086111111 | M80: PM | N80: =TEXT(L80,"h:mm")&" "&M80 -> 2:04 PM | O80: United Kingdom | P80: =PRODUCT(D80,(J80)) -> 25.2
A81: 16695 | B81: 21892 | C81: TRADITIONAL WOODEN CATCH CUP GAME | D81: =ABS(E81) -> 2 | E81: =VALUE(F81) -> 2 | F81: 2 | G81: 510139 | H81: 40325.517 | I81: 1.25 | J81: =VALUE(I81) -> 1.25 | K81: 40325 | L81: 0.51666667 | M81: PM | N81: =TEXT(L81,"h:mm")&" "&M81 -> 12:24 PM | O81: United Kingdom | P81: =PRODUCT(D81,(J81)) -> 2.5
A82: 16670 | B82: 22262 | C82: FELT EGG COSY CHICKEN | D82: =ABS(E82) -> 12 | E82: =VALUE(F82) -> 12 | F82: 12 | G82: 502628 | H82: 40262.65 | I82: 0.85 | J82: =VALUE(I82) -> 0.85 | K82: 40262 | L82: 0.15 | M82: PM | N82: =TEXT(L82,"h:mm")&" "&M82 -> 3:36 PM | O82: United Kingdom | P82: =PRODUCT(D82,(J82)) -> 10.2
A83: 13542 | B83: 48184 | C83: DOOR MAT ENGLISH ROSE | D83: =ABS(E83) -> 1 | E83: =VALUE(F83) -> 1 | F83: 1 | G83: 511851 | H83: 40339.806 | I83: 7.49 | J83: =VALUE(I83) -> 7.49 | K83: 40339 | L83: 0.30625 | M83: PM | N83: =TEXT(L83,"h:mm")&" "&M83 -> 7:21 PM | O83: United Kingdom | P83: =PRODUCT(D83,(J83)) -> 7.49
A84: 14877 | B84: 85206A | C84: CREAM FELT EASTER EGG BASKET | D84: =ABS(E84) -> 2 | E84: =VALUE(F84) -> 2 | F84: 2 | G84: 500326 | H84: 40244.517 | I84: 1.65 | J84: =VALUE(I84) -> 1.65 | K84: 40244 | L84: 0.51736111 | M84: PM | N84: =TEXT(L84,"h:mm")&" "&M84 -> 12:25 PM | O84: United Kingdom | P84: =PRODUCT(D84,(J84)) -> 3.3
A85: 15281 | B85: 22294 | C85: HEART FILIGREE DOVE SMALL | D85: =ABS(E85) -> 24 | E85: =VALUE(F85) -> 24 | F85: 24 | G85: 526089 | H85: 40459.51 | I85: 1.25 | J85: =VALUE(I85) -> 1.25 | K85: 40459 | L85: 0.50972222 | M85: PM | N85: =TEXT(L85,"h:mm")&" "&M85 -> 12:14 PM | O85: United Kingdom | P85: =PRODUCT(D85,(J85)) -> 30
A86: 14625 | B86: 21212 | C86: PACK OF 72 RETRO SPOT CAKE CASES | D86: =ABS(E86) -> 24 | E86: =VALUE(F86) -> 24 | F86: 24 | G86: 518432 | H86: 40399.463 | I86: 0.55 | J86: =VALUE(I86) -> 0.55 | K86: 40399 | L86: 0.4625 | M86: AM | N86: =TEXT(L86,"h:mm")&" "&M86 -> 11:06 AM | O86: United Kingdom | P86: =PRODUCT(D86,(J86)) -> 13.2
A87: 16409 | B87: 84380 | C87: SET OF 3 BUTTERFLY COOKIE CUTTERS | D87: =ABS(E87) -> 12 | E87: =VALUE(F87) -> 12 | F87: 12 | G87: 533547 | H87: 40499.7 | I87: 1.25 | J87: =VALUE(I87) -> 1.25 | K87: 40499 | L87: 0.2 | M87: PM | N87: =TEXT(L87,"h:mm")&" "&M87 -> 4:48 PM | O87: United Kingdom | P87: =PRODUCT(D87,(J87)) -> 15
A88: 15710 | B88: 84580 | C88: MOUSE TOY WITH PINK T-SHIRT | D88: =ABS(E88) -> 2 | E88: =VALUE(F88) -> 2 | F88: 2 | G88: 527754 | H88: 40469.712 | I88: 3.75 | J88: =VALUE(I88) -> 3.75 | K88: 40469 | L88: 0.21180556 | M88: PM | N88: =TEXT(L88,"h:mm")&" "&M88 -> 5:05 PM | O88: United Kingdom | P88: =PRODUCT(D88,(J88)) -> 7.5
A89: 14911 | B89: 21428 | C89: SET3 BOOK BOX GREEN GINGHAM FLOWER | D89: =ABS(E89) -> 4 | E89: =VALUE(F89) -> 4 | F89: 4 | G89: 496008 | H89: 40206.525 | I89: 4.25 | J89: =VALUE(I89) -> 4.25 | K89: 40206 | L89: 0.525 | M89: PM | N89: =TEXT(L89,"h:mm")&" "&M89 -> 12:36 PM | O89: EIRE | P89: =PRODUCT(D89,(J89)) -> 17
A90: 16471 | B90: 84839 | C90: SWEETHEART KEY CABINET | D90: =ABS(E90) -> 2 | E90: =VALUE(F90) -> 2 | F90: 2 | G90: 509071 | H90: 40318.487 | I90: 6.75 | J90: =VALUE(I90) -> 6.75 | K90: 40318 | L90: 0.48680556 | M90: AM | N90: =TEXT(L90,"h:mm")&" "&M90 -> 11:41 AM | O90: United Kingdom | P90: =PRODUCT(D90,(J90)) -> 13.5
A91: 16010 | B91: 21986 | C91: PACK OF 12 PINK POLKADOT TISSUES | D91: =ABS(E91) -> 3 | E91: =VALUE(F91) -> 3 | F91: 3 | G91: 535656 | H91: 40510.472 | I91: 0.29 | J91: =VALUE(I91) -> 0.29 | K91: 40510 | L91: 0.47152778 | M91: AM | N91: =TEXT(L91,"h:mm")&" "&M91 -> 11:19 AM | O91: United Kingdom | P91: =PRODUCT(D91,(J91)) -> 0.87
A92: 13952 | B92: 21535 | C92: RED RETROSPOT SMALL MILK JUG | D92: =ABS(E92) -> 6 | E92: =VALUE(F92) -> 6 | F92: 6 | G92: 522885 | H92: 40438.504 | I92: 2.55 | J92: =VALUE(I92) -> 2.55 | K92: 40438 | L92: 0.50416667 | M92: PM | N92: =TEXT(L92,"h:mm")&" "&M92 -> 12:06 PM | O92: United Kingdom | P92: =PRODUCT(D92,(J92)) -> 15.3
A93: 13206 | B93: 20749 | C93: ASSORTED COLOUR MINI CASES | D93: =ABS(E93) -> 2 | E93: =VALUE(F93) -> 2 | F93: 2 | G93: 502038 | H93: 40259.576 | I93: 7.95 | J93: =VALUE(I93) -> 7.95 | K93: 40259 | L93: 0.075694444 | M93: PM | N93: =TEXT(L93,"h:mm")&" "&M93 -> 1:49 PM | O93: United Kingdom | P93: =PRODUCT(D93,(J93)) -> 15.9
A94: 16767 | B94: 22139 | C94: RETRO SPOT TEA SET CERAMIC 11 PC | D94: =ABS(E94) -> 12 | E94: =VALUE(F94) -> 12 | F94: 12 | G94: 516132 | H94: 40375.644 | I94: 4.95 | J94: =VALUE(I94) -> 4.95 | K94: 40375 | L94: 0.14375 | M94: PM | N94: =TEXT(L94,"h:mm")&" "&M94 -> 3:27 PM | O94: United Kingdom | P94: =PRODUCT(D94,(J94)) -> 59.4
A95: 14210 | B95: 21216 | C95: SET 3 RED SPOT TIN TEA,COFFEE,SUGAR | D95: =ABS(E95) -> 4 | E95: =VALUE(F95) -> 4 | F95: 4 | G95: 511500 | H95: 40337.614 | I95: 4.95 | J95: =VALUE(I95) -> 4.95 | K95: 40337 | L95: 0.11388889 | M95: PM | N95: =TEXT(L95,"h:mm")&" "&M95 -> 2:44 PM | O95: United Kingdom | P95: =PRODUCT(D95,(J95)) -> 19.8
A96: 18102 | B96: 21426 | C96: WOODLAND STORAGE BOX SMALL | D96: =ABS(E96) -> 96 | E96: =VALUE(F96) -> 96 | F96: 96 | G96: 518547 | H96: 40399.771 | I96: 1.25 | J96: =VALUE(I96) -> 1.25 | K96: 40399 | L96: 0.27083333 | M96: PM | N96: =TEXT(L96,"h:mm")&" "&M96 -> 6:30 PM | O96: United Kingdom | P96: =PRODUCT(D96,(J96)) -> 120
A97: 15738 | B97: 22021 | C97: BLUE FELT EASTER EGG BASKET | D97: =ABS(E97) -> 12 | E97: =VALUE(F97) -> 12 | F97: 12 | G97: 501689 | H97: 40255.712 | I97: 1.65 | J97: =VALUE(I97) -> 1.65 | K97: 40255 | L97: 0.21180556 | M97: PM | N97: =TEXT(L97,"h:mm")&" "&M97 -> 5:05 PM | O97: United Kingdom | P97: =PRODUCT(D97,(J97)) -> 19.8
A98: 15581 | B98: 85104 | C98: SILVER GLASS T-LIGHT SET | D98: =ABS(E98) -> 4 | E98: =VALUE(F98) -> 4 | F98: 4 | G98: 489802 | H98: 40149.522 | I98: 2.95 | J98: =VALUE(I98) -> 2.95 | K98: 40149 | L98: 0.52222222 | M98: PM | N98: =TEXT(L98,"h:mm")&" "&M98 -> 12:32 PM | O98: United Kingdom | P98: =PRODUCT(D98,(J98)) -> 11.8
A99: 13131 | B99: 84997B | C99: RED 3 PIECE MINI DOTS CUTLERY SET | D99: =ABS(E99) -> 6 | E99: =VALUE(F99) -> 6 | F99: 6 | G99: 497364 | H99: 40218.408 | I99: 3.75 | J99: =VALUE(I99) -> 3.75 | K99: 40218 | L99: 0.40763889 | M99: AM | N99: =TEXT(L99,"h:mm")&" "&M99 -> 9:47 AM | O99: United Kingdom | P99: =PRODUCT(D99,(J99)) -> 22.5
A100: 18161 | B100: 84879 | C100: ASSORTED COLOUR BIRD ORNAMENT | D100: =ABS(E100) -> 8 | E100: =VALUE(F100) -> 8 | F100: 8 | G100: 535332 | H100: 40507.663 | I100: 1.69 | J100: =VALUE(I100) -> 1.69 | K100: 40507 | L100: 0.16319444 | M100: PM | N100: =TEXT(L100,"h:mm")&" "&M100 -> 3:55 PM | O100: United Kingdom | P100: =PRODUCT(D100,(J100)) -> 13.52
...

Sheet Sheet3
A1: Issue Found | B1: column | C1: Action Taken | D1: Result
A2: Arrangement of columns | B2: Invoice, Customer ID | C2: Rearrnage the columns | D2: Columns arranged
A3: inconsistent text formatting | B3: Country | C3: Formatted text | D3: Consistent text format
A4: Duplicates | B4: country | C4: Remove duplicates | D4: duplicates removed
A5: Missing values | B5: Description, quantity, price, customer ID and country, | C5: Reviewed and documented | D5: Missing Values handled
A6: Data types | B6: All columns | C6: Reviewed and corrected data types | D6: Data types corected
A7: Date and Time were combined | B7: Invoice date | C7: Separated date and time into two different columns | D7: Date and time now in different columns
A8: Some numbers were stored as text | B8: Stock code, quantity and Price | C8: Corrrected the affected cells to their correct data types | D8: Affected cells were standardized to its correct data types
A9: Negative Value | B9: Quantity | C9: Edited negative values to positive values | D9: Nergative Values removed

Sheet Analysis sheet
A1: Country | B1: Total Revenue | D1: Country | E1: Number of Transactions | G1: Country | H1: Average revenue | K1: Row Labels | L1: Sum of Revenue | O1: Row Labels | P1: Sum of Revenue | T1: key Insights
A2: {=_xlfn.UNIQUE(Sheet2!$O$2:$O$1021)} -> United Kingdom | B2: =SUMIF(Sheet2!$O$2:$O$1021,A2,Sheet2!$P$2:$P1021) -> 19278.46 | D2: {=_xlfn.UNIQUE(Sheet2!$O$2:$O$1021)} -> United Kingdom | E2: =COUNTIF(Sheet2!$O$2:$O$1021,D2) -> 922 | G2: {=_xlfn.UNIQUE(Sheet2!O2:O1021)} -> United Kingdom | H2: =AVERAGEIF(Sheet2!$O$2:$O$1021,G2,Sheet2!$P$2:$P$1021) -> 20.909393 | K2: United Kingdom | L2: 19278.46 | O2: GOLD WINE GLASS | P2: 1952.64 | T2: The business generated a total revenue of 24,586.40
A3: EIRE | B3: =SUMIF(Sheet2!$O$2:$O$1021,A3,Sheet2!$P$2:$P1022) -> 1155 | D3: EIRE | E3: =COUNTIF(Sheet2!$O$2:$O$1021,D3) -> 19 | G3: EIRE | H3: =AVERAGEIF(Sheet2!$O$2:$O$1021,G3,Sheet2!$P$2:$P$1021) -> 60.789474 | K3: EIRE | L3: 1155 | O3: ASSORTED FARMYARD ANIMALS IN BUCKET | P3: 993.6 | T3: High transaction doesnot mean high average revenue
A4: Germany | B4: =SUMIF(Sheet2!$O$2:$O$1021,A4,Sheet2!$P$2:$P1023) -> 486.5 | D4: Germany | E4: =COUNTIF(Sheet2!$O$2:$O$1021,D4) -> 21 | G4: Germany | H4: =AVERAGEIF(Sheet2!$O$2:$O$1021,G4,Sheet2!$P$2:$P$1021) -> 23.166667 | K4: Denmark | L4: 1083.6 | O4: RUSTIC WOODEN CABINET, GLASS DOORS | P4: 573.92 | T4: Revenue is concentrated among a small group of top performing countries
A5: France | B5: =SUMIF(Sheet2!$O$2:$O$1021,A5,Sheet2!$P$2:$P1024) -> 796.96 | D5: France | E5: =COUNTIF(Sheet2!$O$2:$O$1021,D5) -> 19 | G5: France | H5: =AVERAGEIF(Sheet2!$O$2:$O$1021,G5,Sheet2!$P$2:$P$1021) -> 41.945263 | K5: Netherlands | L5: 872.13 | O5: CHILDS BREAKFAST SET CIRCUS PARADE | P5: 397.8 | T5: Revenue is not evenly distributed among Products
A6: Singapore | B6: =SUMIF(Sheet2!$O$2:$O$1021,A6,Sheet2!$P$2:$P1025) -> 15 | D6: Singapore | E6: =COUNTIF(Sheet2!$O$2:$O$1021,D6) -> 1 | G6: Singapore | H6: =AVERAGEIF(Sheet2!$O$2:$O$1021,G6,Sheet2!$P$2:$P$1021) -> 15 | K6: France | L6: 796.96 | O6: JUMBO SHOPPER VINTAGE RED PAISLEY | P6: 388.5 | T6: A small number of Products contribute a large share of the total revenue
A7: Belgium | B7: =SUMIF(Sheet2!$O$2:$O$1021,A7,Sheet2!$P$2:$P1026) -> 64.5 | D7: Belgium | E7: =COUNTIF(Sheet2!$O$2:$O$1021,D7) -> 2 | G7: Belgium | H7: =AVERAGEIF(Sheet2!$O$2:$O$1021,G7,Sheet2!$P$2:$P$1021) -> 32.25 | K7: Germany | L7: 486.5 | O7: EDWARDIAN PARASOL BLACK | P7: 362.45
A8: Italy | B8: =SUMIF(Sheet2!$O$2:$O$1021,A8,Sheet2!$P$2:$P1027) -> 29.6 | D8: Italy | E8: =COUNTIF(Sheet2!$O$2:$O$1021,D8) -> 2 | G8: Italy | H8: =AVERAGEIF(Sheet2!$O$2:$O$1021,G8,Sheet2!$P$2:$P$1021) -> 14.8 | K8: Portugal | L8: 226.6 | O8: RECIPE BOX WITH METAL HEART | P8: 349.5
A9: RSA | B9: =SUMIF(Sheet2!$O$2:$O$1021,A9,Sheet2!$P$2:$P1028) -> 19.8 | D9: RSA | E9: =COUNTIF(Sheet2!$O$2:$O$1021,D9) -> 1 | G9: RSA | H9: =AVERAGEIF(Sheet2!$O$2:$O$1021,G9,Sheet2!$P$2:$P$1021) -> 19.8 | K9: Sweden | L9: 155.64 | O9: BLUE POLKADOT PUDDING BOWL | P9: 324.48
A10: Denmark | B10: =SUMIF(Sheet2!$O$2:$O$1021,A10,Sheet2!$P$2:$P1029) -> 1083.6 | D10: Denmark | E10: =COUNTIF(Sheet2!$O$2:$O$1021,D10) -> 2 | G10: Denmark | H10: =AVERAGEIF(Sheet2!$O$2:$O$1021,G10,Sheet2!$P$2:$P$1021) -> 541.8 | K10: Japan | L10: 127.5 | O10: SET/10 RED SPOTTY PARTY CANDLES | P10: 305.28 | R10: Product that generated the highest revenue
A11: Netherlands | B11: =SUMIF(Sheet2!$O$2:$O$1021,A11,Sheet2!$P$2:$P1030) -> 872.13 | D11: Netherlands | E11: =COUNTIF(Sheet2!$O$2:$O$1021,D11) -> 5 | G11: Netherlands | H11: =AVERAGEIF(Sheet2!$O$2:$O$1021,G11,Sheet2!$P$2:$P$1021) -> 174.426 | K11: Channel Islands | L11: 68.98 | O11: ROUND SNACK BOXES SET OF 4 FRUITS | P11: 244.8 | R11: Gold wine Glass
A12: Cyprus | B12: =SUMIF(Sheet2!$O$2:$O$1021,A12,Sheet2!$P$2:$P1031) -> 27.6 | D12: Cyprus | E12: =COUNTIF(Sheet2!$O$2:$O$1021,D12) -> 2 | G12: Cyprus | H12: =AVERAGEIF(Sheet2!$O$2:$O$1021,G12,Sheet2!$P$2:$P$1021) -> 13.8 | K12: Belgium | L12: 64.5 | O12: WHITE HANGING HEART T-LIGHT HOLDER | P12: 240.9
A13: USA | B13: =SUMIF(Sheet2!$O$2:$O$1021,A13,Sheet2!$P$2:$P1032) -> 11.8 | D13: USA | E13: =COUNTIF(Sheet2!$O$2:$O$1021,D13) -> 1 | G13: USA | H13: =AVERAGEIF(Sheet2!$O$2:$O$1021,G13,Sheet2!$P$2:$P$1021) -> 11.8 | K13: Greece | L13: 55.98 | O13: HEART OF WICKER LARGE | P13: 237.8
A14: Channel Islands | B14: =SUMIF(Sheet2!$O$2:$O$1021,A14,Sheet2!$P$2:$P1033) -> 68.98 | D14: Channel Islands | E14: =COUNTIF(Sheet2!$O$2:$O$1021,D14) -> 4 | G14: Channel Islands | H14: =AVERAGEIF(Sheet2!$O$2:$O$1021,G14,Sheet2!$P$2:$P$1021) -> 17.245 | K14: Switzerland | L14: 45.6 | O14: RETROSPOT HEART HOT WATER BOTTLE | P14: 204
A15: Portugal | B15: =SUMIF(Sheet2!$O$2:$O$1021,A15,Sheet2!$P$2:$P1034) -> 226.6 | D15: Portugal | E15: =COUNTIF(Sheet2!$O$2:$O$1021,D15) -> 6 | G15: Portugal | H15: =AVERAGEIF(Sheet2!$O$2:$O$1021,G15,Sheet2!$P$2:$P$1021) -> 37.766667 | K15: Spain | L15: 32.7 | O15: JUMBO BAG SCANDINAVIAN PAISLEY | P15: 204
A16: Japan | B16: =SUMIF(Sheet2!$O$2:$O$1021,A16,Sheet2!$P$2:$P1035) -> 127.5 | D16: Japan | E16: =COUNTIF(Sheet2!$O$2:$O$1021,D16) -> 1 | G16: Japan | H16: =AVERAGEIF(Sheet2!$O$2:$O$1021,G16,Sheet2!$P$2:$P$1021) -> 127.5 | K16: Italy | L16: 29.6 | O16: CERAMIC BOWL WITH STRAWBERRY DESIGN | P16: 201.3
A17: Austria | B17: =SUMIF(Sheet2!$O$2:$O$1021,A17,Sheet2!$P$2:$P1036) -> 13.2 | D17: Austria | E17: =COUNTIF(Sheet2!$O$2:$O$1021,D17) -> 1 | G17: Austria | H17: =AVERAGEIF(Sheet2!$O$2:$O$1021,G17,Sheet2!$P$2:$P$1021) -> 13.2 | K17: Cyprus | L17: 27.6 | O17: POLKADOT CUTLERY 24 PCS IN TRAY | P17: 199
A18: Greece | B18: =SUMIF(Sheet2!$O$2:$O$1021,A18,Sheet2!$P$2:$P1037) -> 55.98 | D18: Greece | E18: =COUNTIF(Sheet2!$O$2:$O$1021,D18) -> 3 | G18: Greece | H18: =AVERAGEIF(Sheet2!$O$2:$O$1021,G18,Sheet2!$P$2:$P$1021) -> 18.66 | K18: RSA | L18: 19.8 | O18: WOOD BLACK BOARD ANT WHITE FINISH | P18: 191.25
A19: Switzerland | B19: =SUMIF(Sheet2!$O$2:$O$1021,A19,Sheet2!$P$2:$P1038) -> 45.6 | D19: Switzerland | E19: =COUNTIF(Sheet2!$O$2:$O$1021,D19) -> 2 | G19: Switzerland | H19: =AVERAGEIF(Sheet2!$O$2:$O$1021,G19,Sheet2!$P$2:$P$1021) -> 22.8 | K19: Singapore | L19: 15 | O19: VINTAGE UNION JACK BUNTING | P19: 187
A20: Sweden | B20: =SUMIF(Sheet2!$O$2:$O$1021,A20,Sheet2!$P$2:$P1039) -> 155.64 | D20: Sweden | E20: =COUNTIF(Sheet2!$O$2:$O$1021,D20) -> 2 | G20: Sweden | H20: =AVERAGEIF(Sheet2!$O$2:$O$1021,G20,Sheet2!$P$2:$P$1021) -> 77.82 | K20: Finland | L20: 15 | O20: JUMBO BAG PINK VINTAGE PAISLEY | P20: 184.5
A21: Spain | B21: =SUMIF(Sheet2!$O$2:$O$1021,A21,Sheet2!$P$2:$P1040) -> 32.7 | D21: Spain | E21: =COUNTIF(Sheet2!$O$2:$O$1021,D21) -> 2 | G21: Spain | H21: =AVERAGEIF(Sheet2!$O$2:$O$1021,G21,Sheet2!$P$2:$P$1021) -> 16.35 | K21: Austria | L21: 13.2 | O21: 36 FOIL HEART CAKE CASES | P21: 177.6
A22: Unspecified | B22: =SUMIF(Sheet2!$O$2:$O$1021,A22,Sheet2!$P$2:$P1041) -> 4.25 | D22: Unspecified | E22: =COUNTIF(Sheet2!$O$2:$O$1021,D22) -> 1 | G22: Unspecified | H22: =AVERAGEIF(Sheet2!$O$2:$O$1021,G22,Sheet2!$P$2:$P$1021) -> 4.25 | K22: USA | L22: 11.8 | O22: RETRO SPOT TEA SET CERAMIC 11 PC | P22: 173.25
A23: Finland | B23: =SUMIF(Sheet2!$O$2:$O$1021,A23,Sheet2!$P$2:$P1042) -> 15 | D23: Finland | E23: =COUNTIF(Sheet2!$O$2:$O$1021,D23) -> 1 | G23: Finland | H23: =AVERAGEIF(Sheet2!$O$2:$O$1021,G23,Sheet2!$P$2:$P$1021) -> 15 | K23: Unspecified | L23: 4.25 | O23: BLUE PARTY BAGS | P23: 169
K24: Grand Total | L24: 24586.4 | O24: RED SPOTTY COFFEE MUG | P24: 168
O25: RETRO SPOT TRADITIONAL TEAPOT | P25: 166.8
O26: JUMBO SHOPPER VINTAGE RED PAISLEY | P26: 165
A27: country with the highest total revenue | B27: United Kingdom | D27: country with the highest number of Transactions | E27: United Kingdom | G27: country with the hughest average transaction revenue | H27: Nethelands | K27: Top five country by total revenue | O27: WOODEN BOX OF DOMINOES | P27: 155.14
K28: United Kingdom | O28: HANGING BAUBLE T-LIGHT HOLDER SMALL | P28: 151.2
K29: EIRE | O29: TEA TIME CAKE STAND IN GIFT BOX | P29: 150.5
K30: Denmark | O30: SET/4 WHITE RETRO STORAGE CUBES | P30: 139.8
K31: Netherlands | O31: PLASTERS IN TIN VINTAGE PAISLEY | P31: 139.2
K32: France | O32: HANGING PHOTO CLIP ROPE LADDER | P32: 139.2
K33: Germany | O33: CINAMMON & ORANGE WREATH | P33: 138.3
O34: MAGIC DRAWING SLATE DOLLY GIRL | P34: 138.24
O35: ASSORTED COLOUR BIRD ORNAMENT | P35: 136.89
O36: WOODLAND STORAGE BOX SMALL | P36: 132.6
O37: WHITE CHERRY LIGHTS | P37: 130.8
O38: PARTY BUNTING | P38: 130.2
O39: REGENCY CAKESTAND 3 TIER | P39: 127.5
O40: STRAWBERRY PICNIC BAG | P40: 127.5
O41: PARTY CONES CARNIVAL ASSORTED | P41: 127.2
O42: SET OF 6 T-LIGHTS WEDDING CAKE | P42: 122.4
O43: GIN + TONIC DIET METAL SIGN | P43: 120.3
O44: HOME BUILDING BLOCK WORD | P44: 119
O45: BROCADE RING PURSE | P45: 115.2
... O744: Grand Total | P744: 24586.4
