Workbook

Sheet Customer_Master
A1: CustomerID | B1: CustomerName | C1: Country
A2: 12346 | B2: Customer 12346 | C2: United Kingdom
A3: 12347 | B3: Customer 12347 | C3: Iceland
A4: 12356 | B4: Customer 12356 | C4: Portugal
A5: 12359 | B5: Customer 12359 | C5: Cyprus
A6: 12369 | B6: Customer 12369 | C6: Austria
A7: 12377 | B7: Customer 12377 | C7: Switzerland
A8: 12380 | B8: Customer 12380 | C8: Belgium
A9: 12388 | B9: Customer 12388 | C9: Australia
A10: 12389 | B10: Customer 12389 | C10: Australia
A11: 12391 | B11: Customer 12391 | C11: Cyprus
A12: 12393 | B12: Customer 12393 | C12: Australia
A13: 12395 | B13: Customer 12395 | C13: Belgium
... A2012: 18287 | B2012: Customer 18287 | C2012: United Kingdom

Sheet Sheet3
A3: Row Labels | B3: Sum of TotalSales | C3: Sum of TotalSales2 | W3: Row Labels | X3: Sum of TotalSales
A4: United Kingdom | B4: 86048.33 | C4: 0.83455542 | D4: Row Labels | E4: Sum of TotalSales | F4: Sum of Quantity | W4: 18102 | X4: 4581.2
A5: Netherlands | B5: 4090.88 | C5: 0.039676145 | D5: ASSORTED FARMYARD ANIMALS IN BUCKET | E5: 993.6 | F5: 3312 | H5: Row Labels | I5: Sum of TotalSales | W5: Customer 18102 | X5: 4581.2
A6: EIRE | B6: 3734.27 | C6: 0.036217498 | D6: WHITE HANGING HEART T-LIGHT HOLDER | E6: 2849.4 | F6: 1076 | H6: 2009 | I6: 8326.03 | W6: 17450 | X6: 3879.96
A7: Germany | B7: 2538.06 | C7: 0.024615838 | D7: VINTAGE UNION JACK DOORSTOP | E7: 3873.98 | F7: 650 | H7: Dec | I7: 8326.03 | W7: Customer 17450 | X7: 3879.96
A8: France | B8: 1558.98 | C8: 0.015120052 | D8: RED/WHITE DOTS RUFFLED UMBRELLA | E8: 1829.1 | F8: 594 | H8: 2010 | I8: 94780.76 | W8: 14646 | X8: 3807.22
A9: Denmark | B9: 1100.1 | C9: 0.01066952 | D9: JUMBO BAG RED RETROSPOT | E9: 828.45 | F9: 471 | H9: Jan | I9: 4982.33 | W9: Customer 14646 | X9: 3807.22
A10: Switzerland | B10: 444.06 | C10: 0.0043067969 | D10: DOORMAT AIRMAIL | E10: 1583.7 | F10: 330 | H10: Feb | I10: 6751.77 | W10: 15061 | X10: 2245.84
A11: Greece | B11: 420.04 | C11: 0.0040738345 | D11: HOME SWEET HOME METAL SIGN | E11: 752.1 | F11: 294 | H11: Mar | I11: 7871.57 | W11: Customer 15061 | X11: 2245.84
A12: Sweden | B12: 392.52 | C12: 0.0038069268 | D12: PAPER CHAIN KIT 50'S CHRISTMAS | E12: 756.55 | F12: 289 | H12: Apr | I12: 4977.62 | W12: 17511 | X12: 2090.18
A13: Portugal | B13: 327.85 | C13: 0.003179713 | D13: GOLD WINE GLASS | E13: 976.32 | F13: 288 | H13: May | I13: 8370.13 | W13: Customer 17511 | X13: 2090.18
A14: Channel Islands | B14: 262.61 | C14: 0.002546971 | D14: REGENCY CAKESTAND 3 TIER | E14: 1032.15 | F14: 89 | H14: Jun | I14: 4302.51 | W14: 14911 | X14: 2004.28
A15: United Arab Emirates | B15: 253 | C15: 0.0024537666 | D15: Grand Total | E15: 15475.35 | F15: 7393 | H15: Jul | I15: 7793.4 | W15: Customer 14911 | X15: 2004.28
A16: Finland | B16: 249.4 | C16: 0.0024188514 | H16: Aug | I16: 7010.15 | W16: 16013 | X16: 1756
A17: Belgium | B17: 227.8 | C17: 0.0022093598 | H17: Sep | I17: 13351.69 | W17: Customer 16013 | X17: 1756
A18: Spain | B18: 212.9 | C18: 0.0020648495 | H18: Oct | I18: 11672.35 | W18: 14156 | X18: 1692.19
A19: Japan | B19: 200.15 | C19: 0.0019411913 | H19: Nov | I19: 13728.1 | W19: Customer 14156 | X19: 1692.19
A20: Australia | B20: 149.4 | C20: 0.0014489831 | H20: Dec | I20: 3969.14 | W20: 13694 | X20: 1173.8
A21: Cyprus | B21: 143.6 | C21: 0.0013927308 | H21: Grand Total | I21: 103106.79 | W21: Customer 13694 | X21: 1173.8
A22: Not Found | B22: 128.5 | C22: 0.0012462807 | W22: 13089 | X22: 1034.17
A23: Italy | B23: 123 | C23: 0.0011929379 | W23: Customer 13089 | X23: 1034.17
A24: Thailand | B24: 120.96 | C24: 0.0011731526 | W24: 13902 | X24: 993.6
A25: Austria | B25: 86.44 | C25: 0.0008383541 | W25: Customer 13902 | X25: 993.6
A26: Unspecified | B26: 69.95 | C26: 0.00067842283 | W26: 16422 | X26: 953.64
A27: Norway | B27: 67.74 | C27: 0.00065698874 | W27: Customer 16422 | X27: 953.64
A28: Singapore | B28: 52.5 | C28: 0.00050918082 | W28: 15311 | X28: 895.42
A29: Malta | B29: 41.55 | C29: 0.00040298025 | W29: Customer 15311 | X29: 895.42
A30: USA | B30: 25 | C30: 0.00024246706 | W30: 13881 | X30: 753.26
A31: RSA | B31: 19.8 | C31: 0.00019203391 | W31: Customer 13881 | X31: 753.26
A32: Iceland | B32: 10.2 | C32: 9.892656e-05 | W32: 16684 | X32: 628.56
A33: Korea | B33: 7.2 | C33: 6.9830513e-05 | W33: Customer 16684 | X33: 628.56
A34: Grand Total | B34: 103106.79 | C34: 1 | W34: 13802 | X34: 600.62
W35: Customer 13802 | X35: 600.62
W36: 12931 | X36: 574.5
W37: Customer 12931 | X37: 574.5
W38: 12678 | X38: 571.2
W39: Customer 12678 | X39: 571.2
W40: 14062 | X40: 550.8
W41: Customer 14062 | X41: 550.8
W42: 13090 | X42: 492.15
W43: Customer 13090 | X43: 492.15
W44: 17850 | X44: 461.26
W45: Customer 17850 | X45: 461.26
W46: 14258 | X46: 450.2
W47: Customer 14258 | X47: 450.2
W48: 16029 | X48: 448.1
W49: Customer 16029 | X49: 448.1
W50: 17675 | X50: 445.5
W51: Customer 17675 | X51: 445.5
W52: 12709 | X52: 415.8
W53: Customer 12709 | X53: 415.8
W54: 14970 | X54: 403.5
W55: Customer 14970 | X55: 403.5
W56: 15748 | X56: 396.9
W57: Customer 15748 | X57: 396.9
W58: 13798 | X58: 386.34
W59: Customer 13798 | X59: 386.34
W60: 16126 | X60: 377.25
W61: Customer 16126 | X61: 377.25
W62: 13001 | X62: 372.54
W63: Customer 13001 | X63: 372.54
W64: 17841 | X64: 357.68
W65: Customer 17841 | X65: 357.68
W66: 15093 | X66: 357
W67: Customer 15093 | X67: 357
W68: 14298 | X68: 342.84
W69: Customer 14298 | X69: 342.84
W70: 14548 | X70: 326.4
W71: Customer 14548 | X71: 326.4
W72: 12921 | X72: 324.86
W73: Customer 12921 | X73: 324.86
W74: 13687 | X74: 324.48
W75: Customer 13687 | X75: 324.48
W76: 14439 | X76: 319.02
W77: Customer 14439 | X77: 319.02
W78: 14680 | X78: 316.9
W79: Customer 14680 | X79: 316.9
W80: 17920 | X80: 310.14
W81: Customer 17920 | X81: 310.14
W82: 13680 | X82: 308.3
W83: Customer 13680 | X83: 308.3
W84: 15856 | X84: 300
W85: Customer 15856 | X85: 300
W86: 13081 | X86: 298.29
W87: Customer 13081 | X87: 298.29
W88: 13564 | X88: 295.69
W89: Customer 13564 | X89: 295.69
W90: 14160 | X90: 290
W91: Customer 14160 | X91: 290
W92: 18092 | X92: 268.8
W93: Customer 18092 | X93: 268.8
W94: 12409 | X94: 267.56
W95: Customer 12409 | X95: 267.56
W96: 17377 | X96: 260.49
W97: Customer 17377 | X97: 260.49
W98: 12739 | X98: 253
W99: Customer 12739 | X99: 253
W100: 15251 | X100: 251.7
W101: Customer 15251 | X101: 251.7
W102: 12748 | X102: 250.81
...

Sheet Transactions
A1: TransactionID | B1: Invoice | C1: StockCode | D1: Description | E1: InvoiceDate | F1: CustomerID | G1: Country | H1: CustomerName | I1: CustomerCountry | J1: Price | K1: Quantity | L1: TotalSales
A2: 1 | B2: 489439 | C2: 85216 | D2: ASSORTED CAKES FRIDGE MAGNETS | E2: 40148.394 | F2: C99991 | G2: France | H2: =_xlfn.XLOOKUP(F2,Customer_Master!$A:$A,Customer_Master!$B:$B,"Not Found") -> Not Found | I2: =_xlfn.XLOOKUP(F2,Customer_Master!$A:$A,Customer_Master!$C:$C,"Not Found") -> Not Found | J2: 0.65 | K2: 12 | L2: =PRODUCT(J2:K2) -> 7.8
A3: 2 | B3: 489439 | C3: 21731 | D3: RED TOADSTOOL LED NIGHT LIGHT | E3: 40148.394 | F3: C99992 | G3: France | H3: =_xlfn.XLOOKUP(F3,Customer_Master!$A:$A,Customer_Master!$B:$B,"Not Found") -> Not Found | I3: =_xlfn.XLOOKUP(F3,Customer_Master!$A:$A,Customer_Master!$C:$C,"Not Found") -> Not Found | J3: 1.65 | K3: 24 | L3: =PRODUCT(J3:K3) -> 39.6
A4: 3 | B4: 489443 | C4: 82580 | D4: BATHROOM METAL SIGN | E4: 40148.41 | F4: C99993 | G4: United Kingdom | H4: =_xlfn.XLOOKUP(F4,Customer_Master!$A:$A,Customer_Master!$B:$B,"Not Found") -> Not Found | I4: =_xlfn.XLOOKUP(F4,Customer_Master!$A:$A,Customer_Master!$C:$C,"Not Found") -> Not Found | J4: 0.55 | K4: 12 | L4: =PRODUCT(J4:K4) -> 6.6
A5: 4 | B5: 489488 | C5: 84997C | D5: BLUE 3 PIECE MINI DOTS CUTLERY SET | E5: 40148.458 | F5: C99994 | G5: United Kingdom | H5: =_xlfn.XLOOKUP(F5,Customer_Master!$A:$A,Customer_Master!$B:$B,"Not Found") -> Not Found | I5: =_xlfn.XLOOKUP(F5,Customer_Master!$A:$A,Customer_Master!$C:$C,"Not Found") -> Not Found | J5: 3.75 | K5: 4 | L5: =PRODUCT(J5:K5) -> 15
A6: 5 | B6: 489514 | C6: 21955 | D6: UNION JACK GUNS & ROSES DOORMAT | E6: 40148.473 | F6: C99995 | G6: United Kingdom | H6: =_xlfn.XLOOKUP(F6,Customer_Master!$A:$A,Customer_Master!$B:$B,"Not Found") -> Not Found | I6: =_xlfn.XLOOKUP(F6,Customer_Master!$A:$A,Customer_Master!$C:$C,"Not Found") -> Not Found | J6: 5.95 | K6: 10 | L6: =PRODUCT(J6:K6) -> 59.5
A7: 6 | B7: 489517 | C7: 21791 | D7: VINTAGE HEADS AND TAILS CARD GAME | E7: 40148.482 | F7: 16329 | G7: United Kingdom | H7: =_xlfn.XLOOKUP(F7,Customer_Master!$A:$A,Customer_Master!$B:$B,"Not Found") -> Customer 16329 | I7: =_xlfn.XLOOKUP(F7,Customer_Master!$A:$A,Customer_Master!$C:$C,"Not Found") -> United Kingdom | J7: 1.25 | K7: 6 | L7: =PRODUCT(J7:K7) -> 7.5
A8: 7 | B8: 489517 | C8: 22130 | D8: PARTY CONE CHRISTMAS DECORATION | E8: 40148.482 | F8: 16329 | G8: United Kingdom | H8: =_xlfn.XLOOKUP(F8,Customer_Master!$A:$A,Customer_Master!$B:$B,"Not Found") -> Customer 16329 | I8: =_xlfn.XLOOKUP(F8,Customer_Master!$A:$A,Customer_Master!$C:$C,"Not Found") -> United Kingdom | J8: 0.85 | K8: 6 | L8: =PRODUCT(J8:K8) -> 5.1
A9: 8 | B9: 489522 | C9: 21869 | D9: POTTING SHED COFFEE MUG | E9: 40148.49 | F9: 15998 | G9: United Kingdom | H9: =_xlfn.XLOOKUP(F9,Customer_Master!$A:$A,Customer_Master!$B:$B,"Not Found") -> Customer 15998 | I9: =_xlfn.XLOOKUP(F9,Customer_Master!$A:$A,Customer_Master!$C:$C,"Not Found") -> United Kingdom | J9: 1.25 | K9: 1 | L9: =PRODUCT(J9:K9) -> 1.25
A10: 9 | B10: 489529 | C10: 22036 | D10: DINOSAUR BIRTHDAY CARD | E10: 40148.494 | F10: 17984 | G10: United Kingdom | H10: =_xlfn.XLOOKUP(F10,Customer_Master!$A:$A,Customer_Master!$B:$B,"Not Found") -> Customer 17984 | I10: =_xlfn.XLOOKUP(F10,Customer_Master!$A:$A,Customer_Master!$C:$C,"Not Found") -> United Kingdom | J10: 0.42 | K10: 12 | L10: =PRODUCT(J10:K10) -> 5.04
A11: 10 | B11: 489532 | C11: 84990 | D11: 60 GOLD AND SILVER FAIRY CAKE CASES | E11: 40148.499 | F11: 13394 | G11: United Kingdom | H11: =_xlfn.XLOOKUP(F11,Customer_Master!$A:$A,Customer_Master!$B:$B,"Not Found") -> Customer 13394 | I11: =_xlfn.XLOOKUP(F11,Customer_Master!$A:$A,Customer_Master!$C:$C,"Not Found") -> United Kingdom | J11: 0.55 | K11: 24 | L11: =PRODUCT(J11:K11) -> 13.2
A12: 11 | B12: 489536 | C12: 21890 | D12: S/6 WOODEN SKITTLES IN COTTON BAG | E12: 40148.509 | F12: 16393 | G12: United Kingdom | H12: =_xlfn.XLOOKUP(F12,Customer_Master!$A:$A,Customer_Master!$B:$B,"Not Found") -> Customer 16393 | I12: =_xlfn.XLOOKUP(F12,Customer_Master!$A:$A,Customer_Master!$C:$C,"Not Found") -> United Kingdom | J12: 2.95 | K12: 1 | L12: =PRODUCT(J12:K12) -> 2.95
A13: 12 | B13: 489536 | C13: 22174 | D13: PHOTO CUBE | E13: 40148.509 | F13: 16393 | G13: United Kingdom | H13: =_xlfn.XLOOKUP(F13,Customer_Master!$A:$A,Customer_Master!$B:$B,"Not Found") -> Customer 16393 | I13: =_xlfn.XLOOKUP(F13,Customer_Master!$A:$A,Customer_Master!$C:$C,"Not Found") -> United Kingdom | J13: 1.65 | K13: 2 | L13: =PRODUCT(J13:K13) -> 3.3
A14: 13 | B14: 489536 | C14: 21581 | D14: SKULLS DESIGN COTTON TOTE BAG | E14: 40148.509 | F14: 16393 | G14: United Kingdom | H14: =_xlfn.XLOOKUP(F14,Customer_Master!$A:$A,Customer_Master!$B:$B,"Not Found") -> Customer 16393 | I14: =_xlfn.XLOOKUP(F14,Customer_Master!$A:$A,Customer_Master!$C:$C,"Not Found") -> United Kingdom | J14: 2.25 | K14: 4 | L14: =PRODUCT(J14:K14) -> 9
A15: 14 | B15: 489537 | C15: 48188 | D15: DOOR MAT WELCOME PUPPIES | E15: 40148.51 | F15: 14040 | G15: United Kingdom | H15: =_xlfn.XLOOKUP(F15,Customer_Master!$A:$A,Customer_Master!$B:$B,"Not Found") -> Customer 14040 | I15: =_xlfn.XLOOKUP(F15,Customer_Master!$A:$A,Customer_Master!$C:$C,"Not Found") -> United Kingdom | J15: 6.75 | K15: 2 | L15: =PRODUCT(J15:K15) -> 13.5
A16: 15 | B16: 489537 | C16: 72800F | D16: 4 IVORY DINNER CANDLES GOLD FLOCK | E16: 40148.51 | F16: 14040 | G16: United Kingdom | H16: =_xlfn.XLOOKUP(F16,Customer_Master!$A:$A,Customer_Master!$B:$B,"Not Found") -> Customer 14040 | I16: =_xlfn.XLOOKUP(F16,Customer_Master!$A:$A,Customer_Master!$C:$C,"Not Found") -> United Kingdom | J16: 2.55 | K16: 1 | L16: =PRODUCT(J16:K16) -> 2.55
A17: 16 | B17: 489539 | C17: 22086 | D17: PAPER CHAIN KIT 50'S CHRISTMAS | E17: 40148.512 | F17: 15061 | G17: United Kingdom | H17: =_xlfn.XLOOKUP(F17,Customer_Master!$A:$A,Customer_Master!$B:$B,"Not Found") -> Customer 15061 | I17: =_xlfn.XLOOKUP(F17,Customer_Master!$A:$A,Customer_Master!$C:$C,"Not Found") -> United Kingdom | J17: 2.55 | K17: 160 | L17: =PRODUCT(J17:K17) -> 408
A18: 17 | B18: 489560 | C18: 21034 | D18: REX CASH+CARRY JUMBO SHOPPER | E18: 40148.539 | F18: 13526 | G18: United Kingdom | H18: =_xlfn.XLOOKUP(F18,Customer_Master!$A:$A,Customer_Master!$B:$B,"Not Found") -> Customer 13526 | I18: =_xlfn.XLOOKUP(F18,Customer_Master!$A:$A,Customer_Master!$C:$C,"Not Found") -> United Kingdom | J18: 0.95 | K18: 3 | L18: =PRODUCT(J18:K18) -> 2.85
A19: 18 | B19: 489562 | C19: 22139 | D19: RETRO SPOT TEA SET CERAMIC 11 PC | E19: 40148.547 | F19: 17998 | G19: United Kingdom | H19: =_xlfn.XLOOKUP(F19,Customer_Master!$A:$A,Customer_Master!$B:$B,"Not Found") -> Customer 17998 | I19: =_xlfn.XLOOKUP(F19,Customer_Master!$A:$A,Customer_Master!$C:$C,"Not Found") -> United Kingdom | J19: 4.95 | K19: 1 | L19: =PRODUCT(J19:K19) -> 4.95
A20: 19 | B20: 489571 | C20: 79323W | D20: WHITE CHERRY LIGHTS | E20: 40148.562 | F20: 15967 | G20: United Kingdom | H20: =_xlfn.XLOOKUP(F20,Customer_Master!$A:$A,Customer_Master!$B:$B,"Not Found") -> Customer 15967 | I20: =_xlfn.XLOOKUP(F20,Customer_Master!$A:$A,Customer_Master!$C:$C,"Not Found") -> United Kingdom | J20: 6.75 | K20: 1 | L20: =PRODUCT(J20:K20) -> 6.75
A21: 20 | B21: 489572 | C21: 37444C | D21: PINK BREAKFAST CUP AND SAUCER | E21: 40148.562 | F21: 17611 | G21: United Kingdom | H21: =_xlfn.XLOOKUP(F21,Customer_Master!$A:$A,Customer_Master!$B:$B,"Not Found") -> Customer 17611 | I21: =_xlfn.XLOOKUP(F21,Customer_Master!$A:$A,Customer_Master!$C:$C,"Not Found") -> United Kingdom | J21: 2.95 | K21: 2 | L21: =PRODUCT(J21:K21) -> 5.9
A22: 21 | B22: 489574 | C22: 21893 | D22: POTTING SHED SEED TIN | E22: 40148.563 | F22: 13097 | G22: United Kingdom | H22: =_xlfn.XLOOKUP(F22,Customer_Master!$A:$A,Customer_Master!$B:$B,"Not Found") -> Customer 13097 | I22: =_xlfn.XLOOKUP(F22,Customer_Master!$A:$A,Customer_Master!$C:$C,"Not Found") -> United Kingdom | J22: 4.25 | K22: 3 | L22: =PRODUCT(J22:K22) -> 12.75
A23: 22 | B23: 489594 | C23: 22055 | D23: MINI CAKE STAND HANGING STRAWBERY | E23: 40148.597 | F23: 15005 | G23: United Kingdom | H23: =_xlfn.XLOOKUP(F23,Customer_Master!$A:$A,Customer_Master!$B:$B,"Not Found") -> Customer 15005 | I23: =_xlfn.XLOOKUP(F23,Customer_Master!$A:$A,Customer_Master!$C:$C,"Not Found") -> United Kingdom | J23: 1.65 | K23: 2 | L23: =PRODUCT(J23:K23) -> 3.3
A24: 23 | B24: 489640 | C24: 22172 | D24: METAL SHELF WITH RAIL | E24: 40148.678 | F24: 17345 | G24: United Kingdom | H24: =_xlfn.XLOOKUP(F24,Customer_Master!$A:$A,Customer_Master!$B:$B,"Not Found") -> Customer 17345 | I24: =_xlfn.XLOOKUP(F24,Customer_Master!$A:$A,Customer_Master!$C:$C,"Not Found") -> United Kingdom | J24: 8.5 | K24: 1 | L24: =PRODUCT(J24:K24) -> 8.5
A25: 24 | B25: 489641 | C25: 79323W | D25: WHITE CHERRY LIGHTS | E25: 40148.679 | F25: 13819 | G25: United Kingdom | H25: =_xlfn.XLOOKUP(F25,Customer_Master!$A:$A,Customer_Master!$B:$B,"Not Found") -> Customer 13819 | I25: =_xlfn.XLOOKUP(F25,Customer_Master!$A:$A,Customer_Master!$C:$C,"Not Found") -> United Kingdom | J25: 6.75 | K25: 4 | L25: =PRODUCT(J25:K25) -> 27
A26: 25 | B26: 489674 | C26: 84970S | D26: HANGING HEART ZINC T-LIGHT HOLDER | E26: 40149.399 | F26: 15602 | G26: United Kingdom | H26: =_xlfn.XLOOKUP(F26,Customer_Master!$A:$A,Customer_Master!$B:$B,"Not Found") -> Customer 15602 | I26: =_xlfn.XLOOKUP(F26,Customer_Master!$A:$A,Customer_Master!$C:$C,"Not Found") -> United Kingdom | J26: 0.85 | K26: 12 | L26: =PRODUCT(J26:K26) -> 10.2
A27: 26 | B27: 489679 | C27: 22322 | D27: BIRD DECORATION GREEN SPOT | E27: 40149.417 | F27: 16163 | G27: United Kingdom | H27: =_xlfn.XLOOKUP(F27,Customer_Master!$A:$A,Customer_Master!$B:$B,"Not Found") -> Customer 16163 | I27: =_xlfn.XLOOKUP(F27,Customer_Master!$A:$A,Customer_Master!$C:$C,"Not Found") -> United Kingdom | J27: 0.85 | K27: 12 | L27: =PRODUCT(J27:K27) -> 10.2
A28: 27 | B28: 489683 | C28: 84970L | D28: SINGLE HEART ZINC T-LIGHT HOLDER | E28: 40149.423 | F28: 16131 | G28: United Kingdom | H28: =_xlfn.XLOOKUP(F28,Customer_Master!$A:$A,Customer_Master!$B:$B,"Not Found") -> Customer 16131 | I28: =_xlfn.XLOOKUP(F28,Customer_Master!$A:$A,Customer_Master!$C:$C,"Not Found") -> United Kingdom | J28: 0.95 | K28: 24 | L28: =PRODUCT(J28:K28) -> 22.8
A29: 28 | B29: 489684 | C29: 22215 | D29: CAKE STAND WHITE TWO TIER LACE | E29: 40149.427 | F29: 14560 | G29: United Kingdom | H29: =_xlfn.XLOOKUP(F29,Customer_Master!$A:$A,Customer_Master!$B:$B,"Not Found") -> Customer 14560 | I29: =_xlfn.XLOOKUP(F29,Customer_Master!$A:$A,Customer_Master!$C:$C,"Not Found") -> United Kingdom | J29: 8.5 | K29: 2 | L29: =PRODUCT(J29:K29) -> 17
A30: 29 | B30: 489765 | C30: 84854 | D30: GIRLY PINK TOOL SET | E30: 40149.481 | F30: 15353 | G30: United Kingdom | H30: =_xlfn.XLOOKUP(F30,Customer_Master!$A:$A,Customer_Master!$B:$B,"Not Found") -> Customer 15353 | I30: =_xlfn.XLOOKUP(F30,Customer_Master!$A:$A,Customer_Master!$C:$C,"Not Found") -> United Kingdom | J30: 4.95 | K30: 1 | L30: =PRODUCT(J30:K30) -> 4.95
A31: 30 | B31: 489785 | C31: 85066 | D31: CREAM SWEETHEART MINI CHEST | E31: 40149.494 | F31: 14653 | G31: United Kingdom | H31: =_xlfn.XLOOKUP(F31,Customer_Master!$A:$A,Customer_Master!$B:$B,"Not Found") -> Customer 14653 | I31: =_xlfn.XLOOKUP(F31,Customer_Master!$A:$A,Customer_Master!$C:$C,"Not Found") -> United Kingdom | J31: 12.75 | K31: 2 | L31: =PRODUCT(J31:K31) -> 25.5
A32: 31 | B32: 489795 | C32: 22189 | D32: CREAM HEART CARD HOLDER | E32: 40149.509 | F32: 14440 | G32: United Kingdom | H32: =_xlfn.XLOOKUP(F32,Customer_Master!$A:$A,Customer_Master!$B:$B,"Not Found") -> Customer 14440 | I32: =_xlfn.XLOOKUP(F32,Customer_Master!$A:$A,Customer_Master!$C:$C,"Not Found") -> United Kingdom | J32: 3.95 | K32: 12 | L32: =PRODUCT(J32:K32) -> 47.4
A33: 32 | B33: 489802 | C33: 85104 | D33: SILVER GLASS T-LIGHT SET | E33: 40149.522 | F33: 15581 | G33: United Kingdom | H33: =_xlfn.XLOOKUP(F33,Customer_Master!$A:$A,Customer_Master!$B:$B,"Not Found") -> Customer 15581 | I33: =_xlfn.XLOOKUP(F33,Customer_Master!$A:$A,Customer_Master!$C:$C,"Not Found") -> United Kingdom | J33: 2.95 | K33: 4 | L33: =PRODUCT(J33:K33) -> 11.8
A34: 33 | B34: 489805 | C34: 84600 | D34: NEW BAROQUE JEWELLERY BOX | E34: 40149.527 | F34: 17377 | G34: United Kingdom | H34: =_xlfn.XLOOKUP(F34,Customer_Master!$A:$A,Customer_Master!$B:$B,"Not Found") -> Customer 17377 | I34: =_xlfn.XLOOKUP(F34,Customer_Master!$A:$A,Customer_Master!$C:$C,"Not Found") -> United Kingdom | J34: 7.95 | K34: 1 | L34: =PRODUCT(J34:K34) -> 7.95
A35: 34 | B35: 489811 | C35: 21622 | D35: VINTAGE UNION JACK CUSHION COVER | E35: 40149.537 | F35: 16210 | G35: United Kingdom | H35: =_xlfn.XLOOKUP(F35,Customer_Master!$A:$A,Customer_Master!$B:$B,"Not Found") -> Customer 16210 | I35: =_xlfn.XLOOKUP(F35,Customer_Master!$A:$A,Customer_Master!$C:$C,"Not Found") -> United Kingdom | J35: 4.95 | K35: 4 | L35: =PRODUCT(J35:K35) -> 19.8
A36: 35 | B36: C489813 | C36: 84472 | D36: PINK AND LILAC QUILTED THROW | E36: 40149.543 | F36: 17867 | G36: United Kingdom | H36: =_xlfn.XLOOKUP(F36,Customer_Master!$A:$A,Customer_Master!$B:$B,"Not Found") -> Customer 17867 | I36: =_xlfn.XLOOKUP(F36,Customer_Master!$A:$A,Customer_Master!$C:$C,"Not Found") -> United Kingdom | J36: 45.95 | K36: -1 | L36: =PRODUCT(J36:K36) -> -45.95
A37: 36 | B37: 489814 | C37: 84270 | D37: ASSTD DESIGN BUBBLE GUM RING | E37: 40149.546 | F37: 14669 | G37: United Kingdom | H37: =_xlfn.XLOOKUP(F37,Customer_Master!$A:$A,Customer_Master!$B:$B,"Not Found") -> Customer 14669 | I37: =_xlfn.XLOOKUP(F37,Customer_Master!$A:$A,Customer_Master!$C:$C,"Not Found") -> United Kingdom | J37: 0.21 | K37: 30 | L37: =PRODUCT(J37:K37) -> 6.3
A38: 37 | B38: 489817 | C38: 22218 | D38: CAKE STAND LACE WHITE | E38: 40149.557 | F38: 16711 | G38: United Kingdom | H38: =_xlfn.XLOOKUP(F38,Customer_Master!$A:$A,Customer_Master!$B:$B,"Not Found") -> Customer 16711 | I38: =_xlfn.XLOOKUP(F38,Customer_Master!$A:$A,Customer_Master!$C:$C,"Not Found") -> United Kingdom | J38: 3.75 | K38: 24 | L38: =PRODUCT(J38:K38) -> 90
A39: 38 | B39: 489822 | C39: 84874B | D39: BLUE TRAVEL FIRST AID KIT | E39: 40149.56 | F39: 14204 | G39: United Kingdom | H39: =_xlfn.XLOOKUP(F39,Customer_Master!$A:$A,Customer_Master!$B:$B,"Not Found") -> Customer 14204 | I39: =_xlfn.XLOOKUP(F39,Customer_Master!$A:$A,Customer_Master!$C:$C,"Not Found") -> United Kingdom | J39: 1.65 | K39: 1 | L39: =PRODUCT(J39:K39) -> 1.65
A40: 39 | B40: 489824 | C40: 20982 | D40: 12 PENCILS TALL TUBE SKULLS | E40: 40149.565 | F40: 16797 | G40: United Kingdom | H40: =_xlfn.XLOOKUP(F40,Customer_Master!$A:$A,Customer_Master!$B:$B,"Not Found") -> Customer 16797 | I40: =_xlfn.XLOOKUP(F40,Customer_Master!$A:$A,Customer_Master!$C:$C,"Not Found") -> United Kingdom | J40: 0.85 | K40: 2 | L40: =PRODUCT(J40:K40) -> 1.7
A41: 40 | B41: 489830 | C41: 21154 | D41: RED SPOTTY OVEN GLOVE | E41: 40149.581 | F41: 13623 | G41: United Kingdom | H41: =_xlfn.XLOOKUP(F41,Customer_Master!$A:$A,Customer_Master!$B:$B,"Not Found") -> Customer 13623 | I41: =_xlfn.XLOOKUP(F41,Customer_Master!$A:$A,Customer_Master!$C:$C,"Not Found") -> United Kingdom | J41: 1.25 | K41: 2 | L41: =PRODUCT(J41:K41) -> 2.5
A42: 41 | B42: 489855 | C42: 21489 | D42: BLUE WHITE SCARF HOT WATER BOTTLE | E42: 40149.607 | F42: 16987 | G42: United Kingdom | H42: =_xlfn.XLOOKUP(F42,Customer_Master!$A:$A,Customer_Master!$B:$B,"Not Found") -> Customer 16987 | I42: =_xlfn.XLOOKUP(F42,Customer_Master!$A:$A,Customer_Master!$C:$C,"Not Found") -> United Kingdom | J42: 3.95 | K42: 3 | L42: =PRODUCT(J42:K42) -> 11.85
A43: 42 | B43: 489866 | C43: 85151 | D43: WELCOME METAL SIGN | E43: 40149.628 | F43: 16200 | G43: United Kingdom | H43: =_xlfn.XLOOKUP(F43,Customer_Master!$A:$A,Customer_Master!$B:$B,"Not Found") -> Customer 16200 | I43: =_xlfn.XLOOKUP(F43,Customer_Master!$A:$A,Customer_Master!$C:$C,"Not Found") -> United Kingdom | J43: 1.25 | K43: 5 | L43: =PRODUCT(J43:K43) -> 6.25
A44: 43 | B44: 489866 | C44: 21485 | D44: RED SPOT HEART HOT WATER BOTTLE | E44: 40149.628 | F44: 16200 | G44: United Kingdom | H44: =_xlfn.XLOOKUP(F44,Customer_Master!$A:$A,Customer_Master!$B:$B,"Not Found") -> Customer 16200 | I44: =_xlfn.XLOOKUP(F44,Customer_Master!$A:$A,Customer_Master!$C:$C,"Not Found") -> United Kingdom | J44: 4.95 | K44: 2 | L44: =PRODUCT(J44:K44) -> 9.9
A45: 44 | B45: 489866 | C45: 21482 | D45: MUSHROOM BLUE HOT WATER BOTTLE | E45: 40149.628 | F45: 16200 | G45: United Kingdom | H45: =_xlfn.XLOOKUP(F45,Customer_Master!$A:$A,Customer_Master!$B:$B,"Not Found") -> Customer 16200 | I45: =_xlfn.XLOOKUP(F45,Customer_Master!$A:$A,Customer_Master!$C:$C,"Not Found") -> United Kingdom | J45: 2.95 | K45: 1 | L45: =PRODUCT(J45:K45) -> 2.95
A46: 45 | B46: 489866 | C46: 84249D | D46: FAIRY CAKE GREETINGS CARD | E46: 40149.628 | F46: 16200 | G46: United Kingdom | H46: =_xlfn.XLOOKUP(F46,Customer_Master!$A:$A,Customer_Master!$B:$B,"Not Found") -> Customer 16200 | I46: =_xlfn.XLOOKUP(F46,Customer_Master!$A:$A,Customer_Master!$C:$C,"Not Found") -> United Kingdom | J46: 0.42 | K46: 12 | L46: =PRODUCT(J46:K46) -> 5.04
A47: 46 | B47: 489866 | C47: 85232A | D47: SET/3 POLKA DOT STACKING TINS | E47: 40149.628 | F47: 16200 | G47: United Kingdom | H47: =_xlfn.XLOOKUP(F47,Customer_Master!$A:$A,Customer_Master!$B:$B,"Not Found") -> Customer 16200 | I47: =_xlfn.XLOOKUP(F47,Customer_Master!$A:$A,Customer_Master!$C:$C,"Not Found") -> United Kingdom | J47: 4.95 | K47: 1 | L47: =PRODUCT(J47:K47) -> 4.95
A48: 47 | B48: 489866 | C48: 82578 | D48: KITCHEN METAL SIGN | E48: 40149.628 | F48: 16200 | G48: United Kingdom | H48: =_xlfn.XLOOKUP(F48,Customer_Master!$A:$A,Customer_Master!$B:$B,"Not Found") -> Customer 16200 | I48: =_xlfn.XLOOKUP(F48,Customer_Master!$A:$A,Customer_Master!$C:$C,"Not Found") -> United Kingdom | J48: 0.55 | K48: 2 | L48: =PRODUCT(J48:K48) -> 1.1
A49: 48 | B49: 489866 | C49: 84288B | D49: SET/2 BLUE NOODLE BASKETS | E49: 40149.628 | F49: 16200 | G49: United Kingdom | H49: =_xlfn.XLOOKUP(F49,Customer_Master!$A:$A,Customer_Master!$B:$B,"Not Found") -> Customer 16200 | I49: =_xlfn.XLOOKUP(F49,Customer_Master!$A:$A,Customer_Master!$C:$C,"Not Found") -> United Kingdom | J49: 1.95 | K49: 12 | L49: =PRODUCT(J49:K49) -> 23.4
A50: 49 | B50: 489866 | C50: 82482 | D50: WOODEN PICTURE FRAME WHITE FINISH | E50: 40149.628 | F50: 16200 | G50: United Kingdom | H50: =_xlfn.XLOOKUP(F50,Customer_Master!$A:$A,Customer_Master!$B:$B,"Not Found") -> Customer 16200 | I50: =_xlfn.XLOOKUP(F50,Customer_Master!$A:$A,Customer_Master!$C:$C,"Not Found") -> United Kingdom | J50: 2.55 | K50: 3 | L50: =PRODUCT(J50:K50) -> 7.65
A51: 50 | B51: 489868 | C51: 22218 | D51: CAKE STAND LACE WHITE | E51: 40149.632 | F51: 15794 | G51: United Kingdom | H51: =_xlfn.XLOOKUP(F51,Customer_Master!$A:$A,Customer_Master!$B:$B,"Not Found") -> Customer 15794 | I51: =_xlfn.XLOOKUP(F51,Customer_Master!$A:$A,Customer_Master!$C:$C,"Not Found") -> United Kingdom | J51: 4.25 | K51: 3 | L51: =PRODUCT(J51:K51) -> 12.75
A52: 51 | B52: 489872 | C52: 22111 | D52: SCOTTIE DOG HOT WATER BOTTLE | E52: 40149.644 | F52: 15615 | G52: United Kingdom | H52: =_xlfn.XLOOKUP(F52,Customer_Master!$A:$A,Customer_Master!$B:$B,"Not Found") -> Customer 15615 | I52: =_xlfn.XLOOKUP(F52,Customer_Master!$A:$A,Customer_Master!$C:$C,"Not Found") -> United Kingdom | J52: 4.95 | K52: 12 | L52: =PRODUCT(J52:K52) -> 59.4
A53: 52 | B53: 489875 | C53: 84912B | D53: GREEN ROSE WASHBAG | E53: 40149.653 | F53: 17841 | G53: United Kingdom | H53: =_xlfn.XLOOKUP(F53,Customer_Master!$A:$A,Customer_Master!$B:$B,"Not Found") -> Customer 17841 | I53: =_xlfn.XLOOKUP(F53,Customer_Master!$A:$A,Customer_Master!$C:$C,"Not Found") -> United Kingdom | J53: 3.75 | K53: 1 | L53: =PRODUCT(J53:K53) -> 3.75
A54: 53 | B54: 489875 | C54: 21622 | D54: VINTAGE UNION JACK CUSHION COVER | E54: 40149.653 | F54: 17841 | G54: United Kingdom | H54: =_xlfn.XLOOKUP(F54,Customer_Master!$A:$A,Customer_Master!$B:$B,"Not Found") -> Customer 17841 | I54: =_xlfn.XLOOKUP(F54,Customer_Master!$A:$A,Customer_Master!$C:$C,"Not Found") -> United Kingdom | J54: 4.95 | K54: 3 | L54: =PRODUCT(J54:K54) -> 14.85
A55: 54 | B55: 489914 | C55: 79323P | D55: PINK CHERRY LIGHTS | E55: 40150.436 | F55: 12921 | G55: United Kingdom | H55: =_xlfn.XLOOKUP(F55,Customer_Master!$A:$A,Customer_Master!$B:$B,"Not Found") -> Customer 12921 | I55: =_xlfn.XLOOKUP(F55,Customer_Master!$A:$A,Customer_Master!$C:$C,"Not Found") -> United Kingdom | J55: 6.75 | K55: 8 | L55: =PRODUCT(J55:K55) -> 54
A56: 55 | B56: 489914 | C56: 20914 | D56: SET/5 RED SPOTTY LID GLASS BOWLS | E56: 40150.436 | F56: 12921 | G56: United Kingdom | H56: =_xlfn.XLOOKUP(F56,Customer_Master!$A:$A,Customer_Master!$B:$B,"Not Found") -> Customer 12921 | I56: =_xlfn.XLOOKUP(F56,Customer_Master!$A:$A,Customer_Master!$C:$C,"Not Found") -> United Kingdom | J56: 2.95 | K56: 6 | L56: =PRODUCT(J56:K56) -> 17.7
A57: 56 | B57: 489916 | C57: 16156N | D57: WRAP, FRIENDSHIP ON GREEN | E57: 40150.442 | F57: 15194 | G57: United Kingdom | H57: =_xlfn.XLOOKUP(F57,Customer_Master!$A:$A,Customer_Master!$B:$B,"Not Found") -> Customer 15194 | I57: =_xlfn.XLOOKUP(F57,Customer_Master!$A:$A,Customer_Master!$C:$C,"Not Found") -> United Kingdom | J57: 0.42 | K57: 25 | L57: =PRODUCT(J57:K57) -> 10.5
A58: 57 | B58: 489935 | C58: 21769 | D58: VINTAGE POST OFFICE CABINET | E58: 40150.452 | F58: 12934 | G58: United Kingdom | H58: =_xlfn.XLOOKUP(F58,Customer_Master!$A:$A,Customer_Master!$B:$B,"Not Found") -> Customer 12934 | I58: =_xlfn.XLOOKUP(F58,Customer_Master!$A:$A,Customer_Master!$C:$C,"Not Found") -> United Kingdom | J58: 79.95 | K58: 1 | L58: =PRODUCT(J58:K58) -> 79.95
A59: 58 | B59: 489998 | C59: 21693 | D59: SMALL HAMMERED SILVER CANDLEPOT | E59: 40150.472 | F59: 15658 | G59: United Kingdom | H59: =_xlfn.XLOOKUP(F59,Customer_Master!$A:$A,Customer_Master!$B:$B,"Not Found") -> Customer 15658 | I59: =_xlfn.XLOOKUP(F59,Customer_Master!$A:$A,Customer_Master!$C:$C,"Not Found") -> United Kingdom | J59: 2.95 | K59: 6 | L59: =PRODUCT(J59:K59) -> 17.7
A60: 59 | B60: 490008 | C60: 22151 | D60: PLACE SETTING WHITE HEART | E60: 40150.507 | F60: 15768 | G60: United Kingdom | H60: =_xlfn.XLOOKUP(F60,Customer_Master!$A:$A,Customer_Master!$B:$B,"Not Found") -> Customer 15768 | I60: =_xlfn.XLOOKUP(F60,Customer_Master!$A:$A,Customer_Master!$C:$C,"Not Found") -> United Kingdom | J60: 0.42 | K60: 2 | L60: =PRODUCT(J60:K60) -> 0.84
A61: 60 | B61: 490009 | C61: 21933 | D61: PINK VINTAGE PAISLEY PICNIC BAG | E61: 40150.509 | F61: 12835 | G61: United Kingdom | H61: =_xlfn.XLOOKUP(F61,Customer_Master!$A:$A,Customer_Master!$B:$B,"Not Found") -> Customer 12835 | I61: =_xlfn.XLOOKUP(F61,Customer_Master!$A:$A,Customer_Master!$C:$C,"Not Found") -> United Kingdom | J61: 2.95 | K61: 1 | L61: =PRODUCT(J61:K61) -> 2.95
A62: 61 | B62: 490012 | C62: 21977 | D62: PACK OF 60 PINK PAISLEY CAKE CASES | E62: 40150.519 | F62: 15179 | G62: United Kingdom | H62: =_xlfn.XLOOKUP(F62,Customer_Master!$A:$A,Customer_Master!$B:$B,"Not Found") -> Customer 15179 | I62: =_xlfn.XLOOKUP(F62,Customer_Master!$A:$A,Customer_Master!$C:$C,"Not Found") -> United Kingdom | J62: 0.55 | K62: 24 | L62: =PRODUCT(J62:K62) -> 13.2
A63: 62 | B63: 490011 | C63: 21181 | D63: PLEASE ONE PERSON METAL SIGN | E63: 40150.519 | F63: 16918 | G63: United Kingdom | H63: =_xlfn.XLOOKUP(F63,Customer_Master!$A:$A,Customer_Master!$B:$B,"Not Found") -> Customer 16918 | I63: =_xlfn.XLOOKUP(F63,Customer_Master!$A:$A,Customer_Master!$C:$C,"Not Found") -> United Kingdom | J63: 2.1 | K63: 3 | L63: =PRODUCT(J63:K63) -> 6.3
A64: 63 | B64: 490063 | C64: 84975 | D64: HEART SHAPED MIRROR | E64: 40150.576 | F64: 17271 | G64: United Kingdom | H64: =_xlfn.XLOOKUP(F64,Customer_Master!$A:$A,Customer_Master!$B:$B,"Not Found") -> Customer 17271 | I64: =_xlfn.XLOOKUP(F64,Customer_Master!$A:$A,Customer_Master!$C:$C,"Not Found") -> United Kingdom | J64: 1.69 | K64: 6 | L64: =PRODUCT(J64:K64) -> 10.14
A65: 64 | B65: 490063 | C65: 85123A | D65: WHITE HANGING HEART T-LIGHT HOLDER | E65: 40150.576 | F65: 17271 | G65: United Kingdom | H65: =_xlfn.XLOOKUP(F65,Customer_Master!$A:$A,Customer_Master!$B:$B,"Not Found") -> Customer 17271 | I65: =_xlfn.XLOOKUP(F65,Customer_Master!$A:$A,Customer_Master!$C:$C,"Not Found") -> United Kingdom | J65: 2.95 | K65: 3 | L65: =PRODUCT(J65:K65) -> 8.85
A66: 65 | B66: 490063 | C66: 84937 | D66: KASHMIR FOLKART TUMBLERS | E66: 40150.576 | F66: 17271 | G66: United Kingdom | H66: =_xlfn.XLOOKUP(F66,Customer_Master!$A:$A,Customer_Master!$B:$B,"Not Found") -> Customer 17271 | I66: =_xlfn.XLOOKUP(F66,Customer_Master!$A:$A,Customer_Master!$C:$C,"Not Found") -> United Kingdom | J66: 2.1 | K66: 6 | L66: =PRODUCT(J66:K66) -> 12.6
A67: 66 | B67: 490072 | C67: 22297 | D67: HEART IVORY TRELLIS SMALL | E67: 40150.603 | F67: 17764 | G67: United Kingdom | H67: =_xlfn.XLOOKUP(F67,Customer_Master!$A:$A,Customer_Master!$B:$B,"Not Found") -> Customer 17764 | I67: =_xlfn.XLOOKUP(F67,Customer_Master!$A:$A,Customer_Master!$C:$C,"Not Found") -> United Kingdom | J67: 1.25 | K67: 3 | L67: =PRODUCT(J67:K67) -> 3.75
A68: 67 | B68: 490083 | C68: 22207 | D68: FRYING PAN UNION FLAG | E68: 40150.649 | F68: 14031 | G68: United Kingdom | H68: =_xlfn.XLOOKUP(F68,Customer_Master!$A:$A,Customer_Master!$B:$B,"Not Found") -> Customer 14031 | I68: =_xlfn.XLOOKUP(F68,Customer_Master!$A:$A,Customer_Master!$C:$C,"Not Found") -> United Kingdom | J68: 4.25 | K68: 10 | L68: =PRODUCT(J68:K68) -> 42.5
A69: 68 | B69: 490093 | C69: 37448 | D69: CERAMIC CAKE DESIGN SPOTTED MUG | E69: 40150.664 | F69: 12949 | G69: United Kingdom | H69: =_xlfn.XLOOKUP(F69,Customer_Master!$A:$A,Customer_Master!$B:$B,"Not Found") -> Customer 12949 | I69: =_xlfn.XLOOKUP(F69,Customer_Master!$A:$A,Customer_Master!$C:$C,"Not Found") -> United Kingdom | J69: 1.49 | K69: 24 | L69: =PRODUCT(J69:K69) -> 35.76
A70: 69 | B70: 490099 | C70: 20753 | D70: RETRO PINK SPOT WASHING UP GLOVES | E70: 40150.675 | F70: 16736 | G70: United Kingdom | H70: =_xlfn.XLOOKUP(F70,Customer_Master!$A:$A,Customer_Master!$B:$B,"Not Found") -> Customer 16736 | I70: =_xlfn.XLOOKUP(F70,Customer_Master!$A:$A,Customer_Master!$C:$C,"Not Found") -> United Kingdom | J70: 2.1 | K70: 6 | L70: =PRODUCT(J70:K70) -> 12.6
A71: 70 | B71: 490101 | C71: 35004S | D71: SET OF 3 SILVER FLYING DUCKS | E71: 40150.683 | F71: 14644 | G71: United Kingdom | H71: =_xlfn.XLOOKUP(F71,Customer_Master!$A:$A,Customer_Master!$B:$B,"Not Found") -> Customer 14644 | I71: =_xlfn.XLOOKUP(F71,Customer_Master!$A:$A,Customer_Master!$C:$C,"Not Found") -> United Kingdom | J71: 6.35 | K71: 6 | L71: =PRODUCT(J71:K71) -> 38.1
A72: 71 | B72: 490106 | C72: 72760B | D72: VINTAGE CREAM 3 BASKET CAKE STAND | E72: 40150.694 | F72: 14898 | G72: United Kingdom | H72: =_xlfn.XLOOKUP(F72,Customer_Master!$A:$A,Customer_Master!$B:$B,"Not Found") -> Customer 14898 | I72: =_xlfn.XLOOKUP(F72,Customer_Master!$A:$A,Customer_Master!$C:$C,"Not Found") -> United Kingdom | J72: 9.95 | K72: 2 | L72: =PRODUCT(J72:K72) -> 19.9
A73: 72 | B73: 490118 | C73: 22319 | D73: HAIRCLIPS FORTIES FABRIC ASSORTED | E73: 40150.74 | F73: 17851 | G73: United Kingdom | H73: =_xlfn.XLOOKUP(F73,Customer_Master!$A:$A,Customer_Master!$B:$B,"Not Found") -> Customer 17851 | I73: =_xlfn.XLOOKUP(F73,Customer_Master!$A:$A,Customer_Master!$C:$C,"Not Found") -> United Kingdom | J73: 0.65 | K73: 12 | L73: =PRODUCT(J73:K73) -> 7.8
A74: 73 | B74: 490142 | C74: 37503 | D74: TEA TIME CAKE STAND IN GIFT BOX | E74: 40151.358 | F74: 14258 | G74: United Kingdom | H74: =_xlfn.XLOOKUP(F74,Customer_Master!$A:$A,Customer_Master!$B:$B,"Not Found") -> Customer 14258 | I74: =_xlfn.XLOOKUP(F74,Customer_Master!$A:$A,Customer_Master!$C:$C,"Not Found") -> United Kingdom | J74: 10.75 | K74: 6 | L74: =PRODUCT(J74:K74) -> 64.5
A75: 74 | B75: 490145 | C75: 22049 | D75: WRAP CHRISTMAS SCREEN PRINT | E75: 40151.394 | F75: 14564 | G75: Channel Islands | H75: =_xlfn.XLOOKUP(F75,Customer_Master!$A:$A,Customer_Master!$B:$B,"Not Found") -> Customer 14564 | I75: =_xlfn.XLOOKUP(F75,Customer_Master!$A:$A,Customer_Master!$C:$C,"Not Found") -> Channel Islands | J75: 0.42 | K75: 25 | L75: =PRODUCT(J75:K75) -> 10.5
A76: 75 | B76: 490156 | C76: 84692 | D76: BOX OF 24 COCKTAIL PARASOLS | E76: 40151.439 | F76: 13093 | G76: United Kingdom | H76: =_xlfn.XLOOKUP(F76,Customer_Master!$A:$A,Customer_Master!$B:$B,"Not Found") -> Customer 13093 | I76: =_xlfn.XLOOKUP(F76,Customer_Master!$A:$A,Customer_Master!$C:$C,"Not Found") -> United Kingdom | J76: 0.42 | K76: 50 | L76: =PRODUCT(J76:K76) -> 21
A77: 76 | B77: 490158 | C77: 20679 | D77: EDWARDIAN PARASOL RED | E77: 40151.449 | F77: 12759 | G77: Netherlands | H77: =_xlfn.XLOOKUP(F77,Customer_Master!$A:$A,Customer_Master!$B:$B,"Not Found") -> Customer 12759 | I77: =_xlfn.XLOOKUP(F77,Customer_Master!$A:$A,Customer_Master!$C:$C,"Not Found") -> Netherlands | J77: 5.95 | K77: 3 | L77: =PRODUCT(J77:K77) -> 17.85
A78: 77 | B78: 490161 | C78: 16169F | D78: WRAP BLIZZARD | E78: 40151.456 | F78: 17160 | G78: United Kingdom | H78: =_xlfn.XLOOKUP(F78,Customer_Master!$A:$A,Customer_Master!$B:$B,"Not Found") -> Customer 17160 | I78: =_xlfn.XLOOKUP(F78,Customer_Master!$A:$A,Customer_Master!$C:$C,"Not Found") -> United Kingdom | J78: 0.42 | K78: 25 | L78: =PRODUCT(J78:K78) -> 10.5
A79: 78 | B79: 490162 | C79: 22093 | D79: MOTORING TISSUE BOX | E79: 40151.463 | F79: 13946 | G79: United Kingdom | H79: =_xlfn.XLOOKUP(F79,Customer_Master!$A:$A,Customer_Master!$B:$B,"Not Found") -> Customer 13946 | I79: =_xlfn.XLOOKUP(F79,Customer_Master!$A:$A,Customer_Master!$C:$C,"Not Found") -> United Kingdom | J79: 1.25 | K79: 1 | L79: =PRODUCT(J79:K79) -> 1.25
A80: 79 | B80: 490281 | C80: 48185 | D80: DOOR MAT FAIRY CAKE | E80: 40151.526 | F80: 13481 | G80: United Kingdom | H80: =_xlfn.XLOOKUP(F80,Customer_Master!$A:$A,Customer_Master!$B:$B,"Not Found") -> Customer 13481 | I80: =_xlfn.XLOOKUP(F80,Customer_Master!$A:$A,Customer_Master!$C:$C,"Not Found") -> United Kingdom | J80: 6.75 | K80: 2 | L80: =PRODUCT(J80:K80) -> 13.5
A81: 80 | B81: 490281 | C81: 48194 | D81: DOORMAT HEARTS | E81: 40151.526 | F81: 13481 | G81: United Kingdom | H81: =_xlfn.XLOOKUP(F81,Customer_Master!$A:$A,Customer_Master!$B:$B,"Not Found") -> Customer 13481 | I81: =_xlfn.XLOOKUP(F81,Customer_Master!$A:$A,Customer_Master!$C:$C,"Not Found") -> United Kingdom | J81: 6.75 | K81: 4 | L81: =PRODUCT(J81:K81) -> 27
A82: 81 | B82: 490279 | C82: 84270 | D82: ASSTD DESIGN BUBBLE GUM RING | E82: 40151.526 | F82: 16891 | G82: United Kingdom | H82: =_xlfn.XLOOKUP(F82,Customer_Master!$A:$A,Customer_Master!$B:$B,"Not Found") -> Customer 16891 | I82: =_xlfn.XLOOKUP(F82,Customer_Master!$A:$A,Customer_Master!$C:$C,"Not Found") -> United Kingdom | J82: 0.21 | K82: 30 | L82: =PRODUCT(J82:K82) -> 6.3
A83: 82 | B83: 490286 | C83: 20688 | D83: BEAUTY SPEED EXPRESSO CUPS | E83: 40151.541 | F83: 14527 | G83: United Kingdom | H83: =_xlfn.XLOOKUP(F83,Customer_Master!$A:$A,Customer_Master!$B:$B,"Not Found") -> Customer 14527 | I83: =_xlfn.XLOOKUP(F83,Customer_Master!$A:$A,Customer_Master!$C:$C,"Not Found") -> United Kingdom | J83: 5.95 | K83: 1 | L83: =PRODUCT(J83:K83) -> 5.95
A84: 83 | B84: 490289 | C84: 85199L | D84: LARGE HANGING IVORY & RED WOOD BIRD | E84: 40151.542 | F84: 15309 | G84: United Kingdom | H84: =_xlfn.XLOOKUP(F84,Customer_Master!$A:$A,Customer_Master!$B:$B,"Not Found") -> Customer 15309 | I84: =_xlfn.XLOOKUP(F84,Customer_Master!$A:$A,Customer_Master!$C:$C,"Not Found") -> United Kingdom | J84: 0.65 | K84: 12 | L84: =PRODUCT(J84:K84) -> 7.8
A85: 84 | B85: 490290 | C85: 21893 | D85: POTTING SHED SEED TIN | E85: 40151.556 | F85: 16325 | G85: United Kingdom | H85: =_xlfn.XLOOKUP(F85,Customer_Master!$A:$A,Customer_Master!$B:$B,"Not Found") -> Customer 16325 | I85: =_xlfn.XLOOKUP(F85,Customer_Master!$A:$A,Customer_Master!$C:$C,"Not Found") -> United Kingdom | J85: 4.25 | K85: 6 | L85: =PRODUCT(J85:K85) -> 25.5
A86: 85 | B86: 490291 | C86: 21917 | D86: SET 12 KIDS WHITE CHALK STICKS | E86: 40151.557 | F86: 16541 | G86: United Kingdom | H86: =_xlfn.XLOOKUP(F86,Customer_Master!$A:$A,Customer_Master!$B:$B,"Not Found") -> Customer 16541 | I86: =_xlfn.XLOOKUP(F86,Customer_Master!$A:$A,Customer_Master!$C:$C,"Not Found") -> United Kingdom | J86: 0.42 | K86: 1 | L86: =PRODUCT(J86:K86) -> 0.42
A87: 86 | B87: 490293 | C87: 21193 | D87: WHITE HONEYCOMB PAPER FAN | E87: 40151.563 | F87: 16699 | G87: United Kingdom | H87: =_xlfn.XLOOKUP(F87,Customer_Master!$A:$A,Customer_Master!$B:$B,"Not Found") -> Customer 16699 | I87: =_xlfn.XLOOKUP(F87,Customer_Master!$A:$A,Customer_Master!$C:$C,"Not Found") -> United Kingdom | J87: 2.1 | K87: 2 | L87: =PRODUCT(J87:K87) -> 4.2
A88: 87 | B88: 490294 | C88: 21144 | D88: PINK POODLE HANGING DECORATION | E88: 40151.57 | F88: 16710 | G88: United Kingdom | H88: =_xlfn.XLOOKUP(F88,Customer_Master!$A:$A,Customer_Master!$B:$B,"Not Found") -> Customer 16710 | I88: =_xlfn.XLOOKUP(F88,Customer_Master!$A:$A,Customer_Master!$C:$C,"Not Found") -> United Kingdom | J88: 0.38 | K88: 24 | L88: =PRODUCT(J88:K88) -> 9.12
A89: 88 | B89: 490300 | C89: 21481 | D89: FAWN BLUE HOT WATER BOTTLE | E89: 40151.597 | F89: 12970 | G89: United Kingdom | H89: =_xlfn.XLOOKUP(F89,Customer_Master!$A:$A,Customer_Master!$B:$B,"Not Found") -> Customer 12970 | I89: =_xlfn.XLOOKUP(F89,Customer_Master!$A:$A,Customer_Master!$C:$C,"Not Found") -> United Kingdom | J89: 2.95 | K89: 1 | L89: =PRODUCT(J89:K89) -> 2.95
A90: 89 | B90: 490312 | C90: 84509A | D90: ENGLISH ROSE PLACEMATS | E90: 40151.636 | F90: 17961 | G90: United Kingdom | H90: =_xlfn.XLOOKUP(F90,Customer_Master!$A:$A,Customer_Master!$B:$B,"Not Found") -> Customer 17961 | I90: =_xlfn.XLOOKUP(F90,Customer_Master!$A:$A,Customer_Master!$C:$C,"Not Found") -> United Kingdom | J90: 3.75 | K90: 1 | L90: =PRODUCT(J90:K90) -> 3.75
A91: 90 | B91: 490323 | C91: 47591A | D91: CAROUSEL DES CHILD'S APRON | E91: 40151.644 | F91: 14087 | G91: United Kingdom | H91: =_xlfn.XLOOKUP(F91,Customer_Master!$A:$A,Customer_Master!$B:$B,"Not Found") -> Customer 14087 | I91: =_xlfn.XLOOKUP(F91,Customer_Master!$A:$A,Customer_Master!$C:$C,"Not Found") -> United Kingdom | J91: 1.65 | K91: 1 | L91: =PRODUCT(J91:K91) -> 1.65
A92: 91 | B92: 490331 | C92: 20717 | D92: STRAWBERRY SHOPPER BAG | E92: 40151.646 | F92: 18181 | G92: United Kingdom | H92: =_xlfn.XLOOKUP(F92,Customer_Master!$A:$A,Customer_Master!$B:$B,"Not Found") -> Customer 18181 | I92: =_xlfn.XLOOKUP(F92,Customer_Master!$A:$A,Customer_Master!$C:$C,"Not Found") -> United Kingdom | J92: 1.25 | K92: 1 | L92: =PRODUCT(J92:K92) -> 1.25
A93: 92 | B93: 490353 | C93: 21070 | D93: VINTAGE BILLBOARD MUG | E93: 40151.692 | F93: 15514 | G93: United Kingdom | H93: =_xlfn.XLOOKUP(F93,Customer_Master!$A:$A,Customer_Master!$B:$B,"Not Found") -> Customer 15514 | I93: =_xlfn.XLOOKUP(F93,Customer_Master!$A:$A,Customer_Master!$C:$C,"Not Found") -> United Kingdom | J93: 1.25 | K93: 6 | L93: =PRODUCT(J93:K93) -> 7.5
A94: 93 | B94: 490371 | C94: 85099C | D94: JUMBO BAG BAROQUE BLACK WHITE | E94: 40152.501 | F94: 13021 | G94: United Kingdom | H94: =_xlfn.XLOOKUP(F94,Customer_Master!$A:$A,Customer_Master!$B:$B,"Not Found") -> Customer 13021 | I94: =_xlfn.XLOOKUP(F94,Customer_Master!$A:$A,Customer_Master!$C:$C,"Not Found") -> United Kingdom | J94: 1.95 | K94: 10 | L94: =PRODUCT(J94:K94) -> 19.5
A95: 94 | B95: 490381 | C95: 21643 | D95: ASSORTED TUTTI FRUTTI MIRROR | E95: 40152.562 | F95: 15420 | G95: United Kingdom | H95: =_xlfn.XLOOKUP(F95,Customer_Master!$A:$A,Customer_Master!$B:$B,"Not Found") -> Customer 15420 | I95: =_xlfn.XLOOKUP(F95,Customer_Master!$A:$A,Customer_Master!$C:$C,"Not Found") -> United Kingdom | J95: 1.25 | K95: 12 | L95: =PRODUCT(J95:K95) -> 15
A96: 95 | B96: 490382 | C96: 85055 | D96: FRENCH ENAMEL UTENSIL HOLDER | E96: 40152.564 | F96: 12359 | G96: Cyprus | H96: =_xlfn.XLOOKUP(F96,Customer_Master!$A:$A,Customer_Master!$B:$B,"Not Found") -> Customer 12359 | I96: =_xlfn.XLOOKUP(F96,Customer_Master!$A:$A,Customer_Master!$C:$C,"Not Found") -> Cyprus | J96: 3.75 | K96: 8 | L96: =PRODUCT(J96:K96) -> 30
A97: 96 | B97: 490382 | C97: 20819 | D97: SILVER TEDDY BEAR | E97: 40152.564 | F97: 12359 | G97: Cyprus | H97: =_xlfn.XLOOKUP(F97,Customer_Master!$A:$A,Customer_Master!$B:$B,"Not Found") -> Customer 12359 | I97: =_xlfn.XLOOKUP(F97,Customer_Master!$A:$A,Customer_Master!$C:$C,"Not Found") -> Cyprus | J97: 3.75 | K97: 4 | L97: =PRODUCT(J97:K97) -> 15
A98: 97 | B98: 490386 | C98: 21262 | D98: WHITE GOOSE FEATHER CHRISTMAS TREE | E98: 40152.623 | F98: 15240 | G98: United Kingdom | H98: =_xlfn.XLOOKUP(F98,Customer_Master!$A:$A,Customer_Master!$B:$B,"Not Found") -> Customer 15240 | I98: =_xlfn.XLOOKUP(F98,Customer_Master!$A:$A,Customer_Master!$C:$C,"Not Found") -> United Kingdom | J98: 16.95 | K98: 1 | L98: =PRODUCT(J98:K98) -> 16.95
A99: 98 | B99: 490387 | C99: 85014B | D99: RED/WHITE DOTS RUFFLED UMBRELLA | E99: 40152.624 | F99: 17850 | G99: United Kingdom | H99: =_xlfn.XLOOKUP(F99,Customer_Master!$A:$A,Customer_Master!$B:$B,"Not Found") -> Customer 17850 | I99: =_xlfn.XLOOKUP(F99,Customer_Master!$A:$A,Customer_Master!$C:$C,"Not Found") -> United Kingdom | J99: 4.95 | K99: 6 | L99: =PRODUCT(J99:K99) -> 29.7
A100: 99 | B100: 490404 | C100: 21908 | D100: CHOCOLATE THIS WAY METAL SIGN | E100: 40153.477 | F100: 16277 | G100: United Kingdom | H100: =_xlfn.XLOOKUP(F100,Customer_Master!$A:$A,Customer_Master!$B:$B,"Not Found") -> Customer 16277 | I100: =_xlfn.XLOOKUP(F100,Customer_Master!$A:$A,Customer_Master!$C:$C,"Not Found") -> United Kingdom | J100: 2.1 | K100: 1 | L100: =PRODUCT(J100:K100) -> 2.1
...
